<?xml version="1.0"?>
<ownershipDocument>

    <schemaVersion>X0609</schemaVersion>

    <documentType>4</documentType>

    <periodOfReport>2026-04-01</periodOfReport>

    <notSubjectToSection16>0</notSubjectToSection16>

    <issuer>
        <issuerCik>0000896878</issuerCik>
        <issuerName>INTUIT INC.</issuerName>
        <issuerTradingSymbol>INTU</issuerTradingSymbol>
        <issuerForeignTradingSymbol></issuerForeignTradingSymbol>
    </issuer>

    <reportingOwner>
        <reportingOwnerId>
            <rptOwnerCik>0001412321</rptOwnerCik>
            <rptOwnerName>Goodarzi Sasan K</rptOwnerName>
        </reportingOwnerId>
        <reportingOwnerAddress>
            <rptOwnerNonUSAddressFlag>false</rptOwnerNonUSAddressFlag>
            <rptOwnerStreet1>C/O INTUIT INC.</rptOwnerStreet1>
            <rptOwnerStreet2>2700 COAST AVENUE</rptOwnerStreet2>
            <rptOwnerCity>MOUNTAIN VIEW</rptOwnerCity>
            <rptOwnerState>CA</rptOwnerState>
            <rptOwnerZipCode>94043</rptOwnerZipCode>
            <rptOwnerStateDescription></rptOwnerStateDescription>
        </reportingOwnerAddress>
        <reportingOwnerRelationship>
            <isDirector>1</isDirector>
            <isOfficer>1</isOfficer>
            <isTenPercentOwner>0</isTenPercentOwner>
            <isOther>0</isOther>
            <officerTitle>CEO, President and Director</officerTitle>
            <otherText></otherText>
        </reportingOwnerRelationship>
    </reportingOwner>

    <aff10b5One>0</aff10b5One>

    <nonDerivativeTable>
        <nonDerivativeTransaction>
            <securityTitle>
                <value>Common Stock</value>
            </securityTitle>
            <transactionDate>
                <value>2026-04-01</value>
            </transactionDate>
            <transactionCoding>
                <transactionFormType>4</transactionFormType>
                <transactionCode>M</transactionCode>
                <equitySwapInvolved>0</equitySwapInvolved>
            </transactionCoding>
            <transactionAmounts>
                <transactionShares>
                    <value>653.529</value>
                </transactionShares>
                <transactionPricePerShare>
                    <value>0</value>
                </transactionPricePerShare>
                <transactionAcquiredDisposedCode>
                    <value>A</value>
                </transactionAcquiredDisposedCode>
            </transactionAmounts>
            <postTransactionAmounts>
                <sharesOwnedFollowingTransaction>
                    <value>14264.957</value>
                </sharesOwnedFollowingTransaction>
            </postTransactionAmounts>
            <ownershipNature>
                <directOrIndirectOwnership>
                    <value>I</value>
                </directOrIndirectOwnership>
                <natureOfOwnership>
                    <value>By Trust</value>
                    <footnoteId id="F1"/>
                </natureOfOwnership>
            </ownershipNature>
        </nonDerivativeTransaction>
        <nonDerivativeTransaction>
            <securityTitle>
                <value>Common Stock</value>
            </securityTitle>
            <transactionDate>
                <value>2026-04-01</value>
            </transactionDate>
            <transactionCoding>
                <transactionFormType>4</transactionFormType>
                <transactionCode>M</transactionCode>
                <equitySwapInvolved>0</equitySwapInvolved>
            </transactionCoding>
            <transactionAmounts>
                <transactionShares>
                    <value>893.612</value>
                </transactionShares>
                <transactionPricePerShare>
                    <value>0</value>
                </transactionPricePerShare>
                <transactionAcquiredDisposedCode>
                    <value>A</value>
                </transactionAcquiredDisposedCode>
            </transactionAmounts>
            <postTransactionAmounts>
                <sharesOwnedFollowingTransaction>
                    <value>15158.569</value>
                </sharesOwnedFollowingTransaction>
            </postTransactionAmounts>
            <ownershipNature>
                <directOrIndirectOwnership>
                    <value>I</value>
                </directOrIndirectOwnership>
                <natureOfOwnership>
                    <value>By Trust</value>
                    <footnoteId id="F1"/>
                </natureOfOwnership>
            </ownershipNature>
        </nonDerivativeTransaction>
        <nonDerivativeTransaction>
            <securityTitle>
                <value>Common Stock</value>
            </securityTitle>
            <transactionDate>
                <value>2026-04-01</value>
            </transactionDate>
            <transactionCoding>
                <transactionFormType>4</transactionFormType>
                <transactionCode>M</transactionCode>
                <equitySwapInvolved>0</equitySwapInvolved>
            </transactionCoding>
            <transactionAmounts>
                <transactionShares>
                    <value>802.006</value>
                </transactionShares>
                <transactionPricePerShare>
                    <value>0</value>
                </transactionPricePerShare>
                <transactionAcquiredDisposedCode>
                    <value>A</value>
                </transactionAcquiredDisposedCode>
            </transactionAmounts>
            <postTransactionAmounts>
                <sharesOwnedFollowingTransaction>
                    <value>15960.575</value>
                </sharesOwnedFollowingTransaction>
            </postTransactionAmounts>
            <ownershipNature>
                <directOrIndirectOwnership>
                    <value>I</value>
                </directOrIndirectOwnership>
                <natureOfOwnership>
                    <value>By Trust</value>
                    <footnoteId id="F1"/>
                </natureOfOwnership>
            </ownershipNature>
        </nonDerivativeTransaction>
        <nonDerivativeTransaction>
            <securityTitle>
                <value>Common Stock</value>
            </securityTitle>
            <transactionDate>
                <value>2026-04-01</value>
            </transactionDate>
            <transactionCoding>
                <transactionFormType>4</transactionFormType>
                <transactionCode>M</transactionCode>
                <equitySwapInvolved>0</equitySwapInvolved>
            </transactionCoding>
            <transactionAmounts>
                <transactionShares>
                    <value>863.013</value>
                </transactionShares>
                <transactionPricePerShare>
                    <value>0</value>
                </transactionPricePerShare>
                <transactionAcquiredDisposedCode>
                    <value>A</value>
                </transactionAcquiredDisposedCode>
            </transactionAmounts>
            <postTransactionAmounts>
                <sharesOwnedFollowingTransaction>
                    <value>16823.588</value>
                </sharesOwnedFollowingTransaction>
            </postTransactionAmounts>
            <ownershipNature>
                <directOrIndirectOwnership>
                    <value>I</value>
                </directOrIndirectOwnership>
                <natureOfOwnership>
                    <value>By Trust</value>
                    <footnoteId id="F1"/>
                </natureOfOwnership>
            </ownershipNature>
        </nonDerivativeTransaction>
        <nonDerivativeTransaction>
            <securityTitle>
                <value>Common Stock</value>
            </securityTitle>
            <transactionDate>
                <value>2026-04-01</value>
            </transactionDate>
            <transactionCoding>
                <transactionFormType>4</transactionFormType>
                <transactionCode>M</transactionCode>
                <equitySwapInvolved>0</equitySwapInvolved>
            </transactionCoding>
            <transactionAmounts>
                <transactionShares>
                    <value>30.832</value>
                </transactionShares>
                <transactionPricePerShare>
                    <value>0</value>
                </transactionPricePerShare>
                <transactionAcquiredDisposedCode>
                    <value>A</value>
                </transactionAcquiredDisposedCode>
            </transactionAmounts>
            <postTransactionAmounts>
                <sharesOwnedFollowingTransaction>
                    <value>16854.42</value>
                </sharesOwnedFollowingTransaction>
            </postTransactionAmounts>
            <ownershipNature>
                <directOrIndirectOwnership>
                    <value>I</value>
                </directOrIndirectOwnership>
                <natureOfOwnership>
                    <value>By Trust</value>
                    <footnoteId id="F1"/>
                </natureOfOwnership>
            </ownershipNature>
        </nonDerivativeTransaction>
        <nonDerivativeTransaction>
            <securityTitle>
                <value>Common Stock</value>
            </securityTitle>
            <transactionDate>
                <value>2026-04-01</value>
            </transactionDate>
            <transactionCoding>
                <transactionFormType>4</transactionFormType>
                <transactionCode>F</transactionCode>
                <equitySwapInvolved>0</equitySwapInvolved>
            </transactionCoding>
            <transactionAmounts>
                <transactionShares>
                    <value>1277.861</value>
                </transactionShares>
                <transactionPricePerShare>
                    <value>432.38</value>
                    <footnoteId id="F2"/>
                </transactionPricePerShare>
                <transactionAcquiredDisposedCode>
                    <value>D</value>
                </transactionAcquiredDisposedCode>
            </transactionAmounts>
            <postTransactionAmounts>
                <sharesOwnedFollowingTransaction>
                    <value>15576.559</value>
                </sharesOwnedFollowingTransaction>
            </postTransactionAmounts>
            <ownershipNature>
                <directOrIndirectOwnership>
                    <value>I</value>
                </directOrIndirectOwnership>
                <natureOfOwnership>
                    <value>By Trust</value>
                    <footnoteId id="F1"/>
                </natureOfOwnership>
            </ownershipNature>
        </nonDerivativeTransaction>
    </nonDerivativeTable>

    <derivativeTable>
        <derivativeTransaction>
            <securityTitle>
                <value>Restricted Stock Units</value>
            </securityTitle>
            <conversionOrExercisePrice>
                <footnoteId id="F3"/>
            </conversionOrExercisePrice>
            <transactionDate>
                <value>2026-04-01</value>
            </transactionDate>
            <transactionCoding>
                <transactionFormType>4</transactionFormType>
                <transactionCode>M</transactionCode>
                <equitySwapInvolved>0</equitySwapInvolved>
            </transactionCoding>
            <transactionAmounts>
                <transactionShares>
                    <value>653.529</value>
                    <footnoteId id="F4"/>
                </transactionShares>
                <transactionPricePerShare>
                    <value>0</value>
                </transactionPricePerShare>
                <transactionAcquiredDisposedCode>
                    <value>D</value>
                </transactionAcquiredDisposedCode>
            </transactionAmounts>
            <exerciseDate>
                <value>2026-04-01</value>
                <footnoteId id="F5"/>
            </exerciseDate>
            <expirationDate>
                <footnoteId id="F6"/>
            </expirationDate>
            <underlyingSecurity>
                <underlyingSecurityTitle>
                    <value>Common Stock</value>
                </underlyingSecurityTitle>
                <underlyingSecurityShares>
                    <value>653.529</value>
                </underlyingSecurityShares>
            </underlyingSecurity>
            <postTransactionAmounts>
                <sharesOwnedFollowingTransaction>
                    <value>653.526</value>
                </sharesOwnedFollowingTransaction>
            </postTransactionAmounts>
            <ownershipNature>
                <directOrIndirectOwnership>
                    <value>D</value>
                </directOrIndirectOwnership>
            </ownershipNature>
        </derivativeTransaction>
        <derivativeTransaction>
            <securityTitle>
                <value>Restricted Stock Units</value>
            </securityTitle>
            <conversionOrExercisePrice>
                <footnoteId id="F3"/>
            </conversionOrExercisePrice>
            <transactionDate>
                <value>2026-04-01</value>
            </transactionDate>
            <transactionCoding>
                <transactionFormType>4</transactionFormType>
                <transactionCode>M</transactionCode>
                <equitySwapInvolved>0</equitySwapInvolved>
            </transactionCoding>
            <transactionAmounts>
                <transactionShares>
                    <value>893.612</value>
                    <footnoteId id="F7"/>
                </transactionShares>
                <transactionPricePerShare>
                    <value>0</value>
                </transactionPricePerShare>
                <transactionAcquiredDisposedCode>
                    <value>D</value>
                </transactionAcquiredDisposedCode>
            </transactionAmounts>
            <exerciseDate>
                <value>2026-04-01</value>
                <footnoteId id="F8"/>
            </exerciseDate>
            <expirationDate>
                <footnoteId id="F6"/>
            </expirationDate>
            <underlyingSecurity>
                <underlyingSecurityTitle>
                    <value>Common Stock</value>
                </underlyingSecurityTitle>
                <underlyingSecurityShares>
                    <value>893.612</value>
                </underlyingSecurityShares>
            </underlyingSecurity>
            <postTransactionAmounts>
                <sharesOwnedFollowingTransaction>
                    <value>4278.072</value>
                </sharesOwnedFollowingTransaction>
            </postTransactionAmounts>
            <ownershipNature>
                <directOrIndirectOwnership>
                    <value>D</value>
                </directOrIndirectOwnership>
            </ownershipNature>
        </derivativeTransaction>
        <derivativeTransaction>
            <securityTitle>
                <value>Restricted Stock Units</value>
            </securityTitle>
            <conversionOrExercisePrice>
                <footnoteId id="F3"/>
            </conversionOrExercisePrice>
            <transactionDate>
                <value>2026-04-01</value>
            </transactionDate>
            <transactionCoding>
                <transactionFormType>4</transactionFormType>
                <transactionCode>M</transactionCode>
                <equitySwapInvolved>0</equitySwapInvolved>
            </transactionCoding>
            <transactionAmounts>
                <transactionShares>
                    <value>802.006</value>
                    <footnoteId id="F9"/>
                </transactionShares>
                <transactionPricePerShare>
                    <value>0</value>
                </transactionPricePerShare>
                <transactionAcquiredDisposedCode>
                    <value>D</value>
                </transactionAcquiredDisposedCode>
            </transactionAmounts>
            <exerciseDate>
                <value>2026-04-01</value>
                <footnoteId id="F10"/>
            </exerciseDate>
            <expirationDate>
                <footnoteId id="F6"/>
            </expirationDate>
            <underlyingSecurity>
                <underlyingSecurityTitle>
                    <value>Common Stock</value>
                </underlyingSecurityTitle>
                <underlyingSecurityShares>
                    <value>802.006</value>
                </underlyingSecurityShares>
            </underlyingSecurity>
            <postTransactionAmounts>
                <sharesOwnedFollowingTransaction>
                    <value>7079.938</value>
                </sharesOwnedFollowingTransaction>
            </postTransactionAmounts>
            <ownershipNature>
                <directOrIndirectOwnership>
                    <value>D</value>
                </directOrIndirectOwnership>
            </ownershipNature>
        </derivativeTransaction>
        <derivativeTransaction>
            <securityTitle>
                <value>Restricted Stock Units</value>
            </securityTitle>
            <conversionOrExercisePrice>
                <footnoteId id="F3"/>
            </conversionOrExercisePrice>
            <transactionDate>
                <value>2026-04-01</value>
            </transactionDate>
            <transactionCoding>
                <transactionFormType>4</transactionFormType>
                <transactionCode>M</transactionCode>
                <equitySwapInvolved>0</equitySwapInvolved>
            </transactionCoding>
            <transactionAmounts>
                <transactionShares>
                    <value>863.013</value>
                    <footnoteId id="F11"/>
                </transactionShares>
                <transactionPricePerShare>
                    <value>0</value>
                </transactionPricePerShare>
                <transactionAcquiredDisposedCode>
                    <value>D</value>
                </transactionAcquiredDisposedCode>
            </transactionAmounts>
            <exerciseDate>
                <value>2026-04-01</value>
                <footnoteId id="F12"/>
            </exerciseDate>
            <expirationDate>
                <footnoteId id="F6"/>
            </expirationDate>
            <underlyingSecurity>
                <underlyingSecurityTitle>
                    <value>Common Stock</value>
                </underlyingSecurityTitle>
                <underlyingSecurityShares>
                    <value>863.013</value>
                </underlyingSecurityShares>
            </underlyingSecurity>
            <postTransactionAmounts>
                <sharesOwnedFollowingTransaction>
                    <value>11067.137</value>
                </sharesOwnedFollowingTransaction>
            </postTransactionAmounts>
            <ownershipNature>
                <directOrIndirectOwnership>
                    <value>D</value>
                </directOrIndirectOwnership>
            </ownershipNature>
        </derivativeTransaction>
        <derivativeTransaction>
            <securityTitle>
                <value>Restricted Stock Units</value>
            </securityTitle>
            <conversionOrExercisePrice>
                <footnoteId id="F3"/>
            </conversionOrExercisePrice>
            <transactionDate>
                <value>2026-04-01</value>
            </transactionDate>
            <transactionCoding>
                <transactionFormType>4</transactionFormType>
                <transactionCode>M</transactionCode>
                <equitySwapInvolved>0</equitySwapInvolved>
            </transactionCoding>
            <transactionAmounts>
                <transactionShares>
                    <value>30.832</value>
                </transactionShares>
                <transactionPricePerShare>
                    <value>0</value>
                </transactionPricePerShare>
                <transactionAcquiredDisposedCode>
                    <value>D</value>
                </transactionAcquiredDisposedCode>
            </transactionAmounts>
            <exerciseDate>
                <value>2026-04-01</value>
                <footnoteId id="F13"/>
            </exerciseDate>
            <expirationDate>
                <footnoteId id="F6"/>
            </expirationDate>
            <underlyingSecurity>
                <underlyingSecurityTitle>
                    <value>Common Stock</value>
                </underlyingSecurityTitle>
                <underlyingSecurityShares>
                    <value>30.832</value>
                </underlyingSecurityShares>
            </underlyingSecurity>
            <postTransactionAmounts>
                <sharesOwnedFollowingTransaction>
                    <value>10980.474</value>
                </sharesOwnedFollowingTransaction>
            </postTransactionAmounts>
            <ownershipNature>
                <directOrIndirectOwnership>
                    <value>D</value>
                </directOrIndirectOwnership>
            </ownershipNature>
        </derivativeTransaction>
    </derivativeTable>

    <footnotes>
        <footnote id="F1">Shares held in Goodarzi Rev Trust u/a Dtd 5/18/2012 of which reporting person is a trustee.</footnote>
        <footnote id="F2">Fair market value of Intuit Inc. common stock on date of grant; restricted stock units awarded pursuant to reporting person's election to receive payment of director's fees in the form of restricted stock units.</footnote>
        <footnote id="F3">1-for-1</footnote>
        <footnote id="F4">Represents 653.529 vested restricted stock units which were subject to a one year deferred release.</footnote>
        <footnote id="F5">Represents release date for these vested restricted stock units.</footnote>
        <footnote id="F6">Restricted stock units do not expire; they either vest or are canceled prior to vesting date.</footnote>
        <footnote id="F7">Represents 848.437 vested restricted stock units which were subject to a one year deferred release and 45.175 vested restricted stock units for which release was accelerated to accommodate tax withholding obligations in connection with restricted stock units which vested on 4/1/2026 but are subject to deferred release.</footnote>
        <footnote id="F8">Represents release date for 848.437 vested restricted stock units and vesting and release date for 45.175 restricted stock units.</footnote>
        <footnote id="F9">Represents 766.263 vested restricted stock units which were subject to a one year deferred release and 35.743 vested restricted stock units for which release was accelerated to accommodate tax withholding obligations in connection with restricted stock units which vested on 4/1/2026 but are subject to deferred release.</footnote>
        <footnote id="F10">Represents release date for 766.263 vested restricted stock units and vesting and release date for 35.743 restricted stock units.</footnote>
        <footnote id="F11">Represents 824.549 vested restricted stock units which were subject to a one year deferred release and 38.464 vested restricted stock units for which release was accelerated to accommodate tax withholding obligations in connection with restricted stock units which vested on 4/1/2026 but are subject to deferred release.</footnote>
        <footnote id="F12">Represents release date for 824.549 vested restricted stock units and vesting and release date for 38.464 restricted stock units.</footnote>
        <footnote id="F13">Represents vesting and release date for this portion of restricted stock units to accommodate tax withholding obligations in connection with vesting and deferred release of certain restricted stock units granted on 7/24/2025.</footnote>
    </footnotes>

    <remarks></remarks>

    <ownerSignature>
        <signatureName>/s/ Erick Rivero, by power-of-attorney</signatureName>
        <signatureDate>2026-04-03</signatureDate>
    </ownerSignature>
</ownershipDocument>
