<?xml version="1.0"?>
<ownershipDocument>

    <schemaVersion>X0609</schemaVersion>

    <documentType>4</documentType>

    <periodOfReport>2026-05-07</periodOfReport>

    <issuer>
        <issuerCik>0001110803</issuerCik>
        <issuerName>ILLUMINA, INC.</issuerName>
        <issuerTradingSymbol>ILMN</issuerTradingSymbol>
        <issuerForeignTradingSymbol></issuerForeignTradingSymbol>
    </issuer>

    <reportingOwner>
        <reportingOwnerId>
            <rptOwnerCik>0001307631</rptOwnerCik>
            <rptOwnerName>Meister Keith A.</rptOwnerName>
        </reportingOwnerId>
        <reportingOwnerAddress>
            <rptOwnerNonUSAddressFlag>false</rptOwnerNonUSAddressFlag>
            <rptOwnerStreet1>C/O CORVEX MANAGEMENT LP</rptOwnerStreet1>
            <rptOwnerStreet2>667 MADISON AVENUE</rptOwnerStreet2>
            <rptOwnerCity>NEW YORK</rptOwnerCity>
            <rptOwnerState>NY</rptOwnerState>
            <rptOwnerZipCode>10065</rptOwnerZipCode>
            <rptOwnerStateDescription></rptOwnerStateDescription>
        </reportingOwnerAddress>
        <reportingOwnerRelationship>
            <isDirector>true</isDirector>
        </reportingOwnerRelationship>
    </reportingOwner>

    <aff10b5One>false</aff10b5One>

    <nonDerivativeTable>
        <nonDerivativeTransaction>
            <securityTitle>
                <value>Common Stock</value>
            </securityTitle>
            <transactionDate>
                <value>2026-05-07</value>
            </transactionDate>
            <transactionCoding>
                <transactionFormType>4</transactionFormType>
                <transactionCode>X</transactionCode>
                <equitySwapInvolved>1</equitySwapInvolved>
                <footnoteId id="F3"/>
                <footnoteId id="F5"/>
            </transactionCoding>
            <transactionAmounts>
                <transactionShares>
                    <value>9236</value>
                </transactionShares>
                <transactionPricePerShare>
                    <value>102.82</value>
                </transactionPricePerShare>
                <transactionAcquiredDisposedCode>
                    <value>A</value>
                </transactionAcquiredDisposedCode>
            </transactionAmounts>
            <postTransactionAmounts>
                <sharesOwnedFollowingTransaction>
                    <value>3838744</value>
                </sharesOwnedFollowingTransaction>
            </postTransactionAmounts>
            <ownershipNature>
                <directOrIndirectOwnership>
                    <value>I</value>
                </directOrIndirectOwnership>
                <natureOfOwnership>
                    <value>See Footnotes</value>
                    <footnoteId id="F1"/>
                    <footnoteId id="F2"/>
                </natureOfOwnership>
            </ownershipNature>
        </nonDerivativeTransaction>
        <nonDerivativeTransaction>
            <securityTitle>
                <value>Common Stock</value>
            </securityTitle>
            <transactionDate>
                <value>2026-05-07</value>
            </transactionDate>
            <transactionCoding>
                <transactionFormType>4</transactionFormType>
                <transactionCode>J</transactionCode>
                <equitySwapInvolved>1</equitySwapInvolved>
                <footnoteId id="F3"/>
                <footnoteId id="F5"/>
            </transactionCoding>
            <transactionAmounts>
                <transactionShares>
                    <value>9236</value>
                </transactionShares>
                <transactionPricePerShare>
                    <value>140.25</value>
                </transactionPricePerShare>
                <transactionAcquiredDisposedCode>
                    <value>D</value>
                </transactionAcquiredDisposedCode>
            </transactionAmounts>
            <postTransactionAmounts>
                <sharesOwnedFollowingTransaction>
                    <value>3829508</value>
                </sharesOwnedFollowingTransaction>
            </postTransactionAmounts>
            <ownershipNature>
                <directOrIndirectOwnership>
                    <value>I</value>
                </directOrIndirectOwnership>
                <natureOfOwnership>
                    <value>See Footnotes</value>
                    <footnoteId id="F1"/>
                    <footnoteId id="F2"/>
                </natureOfOwnership>
            </ownershipNature>
        </nonDerivativeTransaction>
        <nonDerivativeTransaction>
            <securityTitle>
                <value>Common Stock</value>
            </securityTitle>
            <transactionDate>
                <value>2026-05-11</value>
            </transactionDate>
            <transactionCoding>
                <transactionFormType>4</transactionFormType>
                <transactionCode>X</transactionCode>
                <equitySwapInvolved>1</equitySwapInvolved>
                <footnoteId id="F4"/>
                <footnoteId id="F5"/>
            </transactionCoding>
            <transactionAmounts>
                <transactionShares>
                    <value>79568</value>
                </transactionShares>
                <transactionPricePerShare>
                    <value>102.82</value>
                </transactionPricePerShare>
                <transactionAcquiredDisposedCode>
                    <value>A</value>
                </transactionAcquiredDisposedCode>
            </transactionAmounts>
            <postTransactionAmounts>
                <sharesOwnedFollowingTransaction>
                    <value>3909076</value>
                </sharesOwnedFollowingTransaction>
            </postTransactionAmounts>
            <ownershipNature>
                <directOrIndirectOwnership>
                    <value>I</value>
                </directOrIndirectOwnership>
                <natureOfOwnership>
                    <value>See Footnotes</value>
                    <footnoteId id="F1"/>
                    <footnoteId id="F2"/>
                </natureOfOwnership>
            </ownershipNature>
        </nonDerivativeTransaction>
        <nonDerivativeTransaction>
            <securityTitle>
                <value>Common Stock</value>
            </securityTitle>
            <transactionDate>
                <value>2026-05-11</value>
            </transactionDate>
            <transactionCoding>
                <transactionFormType>4</transactionFormType>
                <transactionCode>J</transactionCode>
                <equitySwapInvolved>1</equitySwapInvolved>
                <footnoteId id="F4"/>
                <footnoteId id="F5"/>
            </transactionCoding>
            <transactionAmounts>
                <transactionShares>
                    <value>79568</value>
                </transactionShares>
                <transactionPricePerShare>
                    <value>143.45</value>
                </transactionPricePerShare>
                <transactionAcquiredDisposedCode>
                    <value>D</value>
                </transactionAcquiredDisposedCode>
            </transactionAmounts>
            <postTransactionAmounts>
                <sharesOwnedFollowingTransaction>
                    <value>3829508</value>
                </sharesOwnedFollowingTransaction>
            </postTransactionAmounts>
            <ownershipNature>
                <directOrIndirectOwnership>
                    <value>I</value>
                </directOrIndirectOwnership>
                <natureOfOwnership>
                    <value>See Footnotes</value>
                    <footnoteId id="F1"/>
                    <footnoteId id="F2"/>
                </natureOfOwnership>
            </ownershipNature>
        </nonDerivativeTransaction>
        <nonDerivativeHolding>
            <securityTitle>
                <value>Common Stock</value>
            </securityTitle>
            <postTransactionAmounts>
                <sharesOwnedFollowingTransaction>
                    <value>4566</value>
                </sharesOwnedFollowingTransaction>
            </postTransactionAmounts>
            <ownershipNature>
                <directOrIndirectOwnership>
                    <value>D</value>
                </directOrIndirectOwnership>
            </ownershipNature>
        </nonDerivativeHolding>
    </nonDerivativeTable>

    <derivativeTable>
        <derivativeTransaction>
            <securityTitle>
                <value>Equity Swap (right to buy)</value>
            </securityTitle>
            <conversionOrExercisePrice>
                <value>102.82</value>
            </conversionOrExercisePrice>
            <transactionDate>
                <value>2026-05-07</value>
            </transactionDate>
            <transactionCoding>
                <transactionFormType>4</transactionFormType>
                <transactionCode>X</transactionCode>
                <equitySwapInvolved>1</equitySwapInvolved>
                <footnoteId id="F3"/>
                <footnoteId id="F5"/>
            </transactionCoding>
            <transactionAmounts>
                <transactionShares>
                    <value>9236</value>
                </transactionShares>
                <transactionPricePerShare>
                    <footnoteId id="F3"/>
                </transactionPricePerShare>
                <transactionAcquiredDisposedCode>
                    <value>D</value>
                </transactionAcquiredDisposedCode>
            </transactionAmounts>
            <exerciseDate>
                <footnoteId id="F3"/>
            </exerciseDate>
            <expirationDate>
                <value>2028-02-11</value>
            </expirationDate>
            <underlyingSecurity>
                <underlyingSecurityTitle>
                    <value>Common Stock</value>
                </underlyingSecurityTitle>
                <underlyingSecurityShares>
                    <value>9236</value>
                </underlyingSecurityShares>
            </underlyingSecurity>
            <postTransactionAmounts>
                <sharesOwnedFollowingTransaction>
                    <value>359508</value>
                </sharesOwnedFollowingTransaction>
            </postTransactionAmounts>
            <ownershipNature>
                <directOrIndirectOwnership>
                    <value>I</value>
                </directOrIndirectOwnership>
                <natureOfOwnership>
                    <value>See Footnotes</value>
                    <footnoteId id="F1"/>
                    <footnoteId id="F2"/>
                </natureOfOwnership>
            </ownershipNature>
        </derivativeTransaction>
        <derivativeTransaction>
            <securityTitle>
                <value>Equity Swap (right to buy)</value>
            </securityTitle>
            <conversionOrExercisePrice>
                <value>102.82</value>
            </conversionOrExercisePrice>
            <transactionDate>
                <value>2026-05-11</value>
            </transactionDate>
            <transactionCoding>
                <transactionFormType>4</transactionFormType>
                <transactionCode>X</transactionCode>
                <equitySwapInvolved>1</equitySwapInvolved>
                <footnoteId id="F4"/>
                <footnoteId id="F5"/>
            </transactionCoding>
            <transactionAmounts>
                <transactionShares>
                    <value>79568</value>
                </transactionShares>
                <transactionPricePerShare>
                    <footnoteId id="F4"/>
                </transactionPricePerShare>
                <transactionAcquiredDisposedCode>
                    <value>D</value>
                </transactionAcquiredDisposedCode>
            </transactionAmounts>
            <exerciseDate>
                <footnoteId id="F3"/>
            </exerciseDate>
            <expirationDate>
                <value>2028-02-11</value>
            </expirationDate>
            <underlyingSecurity>
                <underlyingSecurityTitle>
                    <value>Common Stock</value>
                </underlyingSecurityTitle>
                <underlyingSecurityShares>
                    <value>79568</value>
                </underlyingSecurityShares>
            </underlyingSecurity>
            <postTransactionAmounts>
                <sharesOwnedFollowingTransaction>
                    <value>279940</value>
                </sharesOwnedFollowingTransaction>
            </postTransactionAmounts>
            <ownershipNature>
                <directOrIndirectOwnership>
                    <value>I</value>
                </directOrIndirectOwnership>
                <natureOfOwnership>
                    <value>See Footnotes</value>
                    <footnoteId id="F1"/>
                    <footnoteId id="F2"/>
                </natureOfOwnership>
            </ownershipNature>
        </derivativeTransaction>
    </derivativeTable>

    <footnotes>
        <footnote id="F1">These securities of Illumina, Inc. (the &quot;Issuer&quot;) are held for the accounts of certain private investment funds (collectively, the &quot;Corvex Funds&quot;) for which Corvex Management LP (&quot;Corvex&quot;) acts as investment adviser, including Corvex Master Fund LP and Corvex Select Equity Master Fund LP. The general partner of Corvex is controlled by Keith Meister.</footnote>
        <footnote id="F2">For the purposes of this filing, each of Corvex and Mr. Meister disclaims beneficial ownership of the reported securities except to the extent of his or its pecuniary interest therein. This filing shall not be deemed an admission that Corvex or Mr. Meister is the beneficial owner of any of the reported securities for purposes of Section 16 of the Securities Exchange Act of 1934, as amended, or otherwise.</footnote>
        <footnote id="F3">As previously reported, the Corvex Funds had entered into equity swaps that represented an aggregate economic long-side exposure comparable to a notional interest in 368,744 shares of common stock of the Issuer. Under the terms of the swaps, the value to be received or paid upon termination of a swap will be determined by the difference in the market price per notional share of common stock on the date of termination as compared to the cost of such notional share of common stock at the time of entry into the swap. On May 7, 2026, upon partial termination of the swaps as reported in Table II above, the swaps counterparty paid to the Corvex Funds $1,295,349, representing $140.25 per share for each of the 9,236 notional shares subject to the termination (the market price of the common stock on the date of the partial termination), offset by $949,645.52, representing $102.82 for each of such 9,236 notional shares.</footnote>
        <footnote id="F4">In addition, on May 11, 2026, upon partial termination of the swaps as reported in Table II above, the swaps counterparty paid to the Corvex Funds $11,414,029.60, representing $143.45 per share for each of the 79,568 notional shares subject to the termination (the market price of the common stock on the date of the partial termination), offset by $8,181,181.76, representing $102.82 for each of such 79,568 notional shares.</footnote>
        <footnote id="F5">The partial termination of the equity swaps and the reported purchases of common stock in connection therewith are deemed exempt from Section 16(b) of the Securities Exchange Act of 1934 pursuant to Rule 16b-6(b) thereunder. The remaining swaps terminate on February 11, 2028, and have a cost basis of $102.82 per notional share of common stock. All balances will be settled in cash by default. At the option of the Corvex Funds, the remaining portion of the swaps may be physically settled by the Corvex Funds acquiring 279,940 shares of common stock from the counterparty at $102.82 per share.</footnote>
    </footnotes>

    <ownerSignature>
        <signatureName>/s/ Keith Meister</signatureName>
        <signatureDate>2026-05-11</signatureDate>
    </ownerSignature>
</ownershipDocument>
