{
  "ticker": "NVDA",
  "cik": "0001045810",
  "days": 90,
  "fetched_at": "2026-05-21T09:52:35+00:00",
  "n_filings": 19,
  "n_transactions": 62,
  "n_open_market": 38,
  "n_purchases": 0,
  "n_sales": 38,
  "n_10b5_1": 40,
  "n_derivative": 0,
  "distinct_owners": 10,
  "filings": [
    {
      "accession": "0001199039-26-000003",
      "form": "4",
      "filed": "2026-03-24",
      "period_of_report": "2026-03-20",
      "issuer": {
        "cik": "0001045810",
        "name": "NVIDIA CORP",
        "ticker": "NVDA"
      },
      "owner": {
        "cik": "0001199039",
        "name": "STEVENS MARK A",
        "is_director": true,
        "is_officer": false,
        "is_10pct_owner": false,
        "is_other": false,
        "title": null
      },
      "n_reporting_owners": 1,
      "doc_aff_10b5_1": false,
      "transactions": [
        {
          "security": "Common Stock",
          "date": "2026-03-20",
          "code": "S",
          "is_open_market": true,
          "is_10b5_1": false,
          "is_derivative": false,
          "shares": 100000.0,
          "price": 172.6068,
          "value": 17260680.0,
          "acquired_disposed": "D",
          "shares_owned_after": 7521453.0,
          "footnote_refs": [
            "F1",
            "F2"
          ]
        },
        {
          "security": "Common Stock",
          "date": "2026-03-20",
          "code": "S",
          "is_open_market": true,
          "is_10b5_1": false,
          "is_derivative": false,
          "shares": 121682.0,
          "price": 174.5685,
          "value": 21241844.217,
          "acquired_disposed": "D",
          "shares_owned_after": 7399771.0,
          "footnote_refs": [
            "F2",
            "F3"
          ]
        }
      ]
    },
    {
      "accession": "0001725292-26-000002",
      "form": "4",
      "filed": "2026-03-20",
      "period_of_report": "2026-03-19",
      "issuer": {
        "cik": "0001045810",
        "name": "NVIDIA CORP",
        "ticker": "NVDA"
      },
      "owner": {
        "cik": "0001725292",
        "name": "Shah Aarti S.",
        "is_director": true,
        "is_officer": false,
        "is_10pct_owner": false,
        "is_other": false,
        "title": null
      },
      "n_reporting_owners": 1,
      "doc_aff_10b5_1": true,
      "transactions": [
        {
          "security": "Common",
          "date": "2026-03-19",
          "code": "S",
          "is_open_market": true,
          "is_10b5_1": true,
          "is_derivative": false,
          "shares": 8516.0,
          "price": 176.2743,
          "value": 1501151.9388000001,
          "acquired_disposed": "D",
          "shares_owned_after": 46491.0,
          "footnote_refs": [
            "F1",
            "F2"
          ]
        },
        {
          "security": "Common",
          "date": "2026-03-19",
          "code": "S",
          "is_open_market": true,
          "is_10b5_1": true,
          "is_derivative": false,
          "shares": 10282.0,
          "price": 177.0565,
          "value": 1820494.933,
          "acquired_disposed": "D",
          "shares_owned_after": 36209.0,
          "footnote_refs": [
            "F1",
            "F3"
          ]
        },
        {
          "security": "Common",
          "date": "2026-03-19",
          "code": "S",
          "is_open_market": true,
          "is_10b5_1": true,
          "is_derivative": false,
          "shares": 202.0,
          "price": 177.7335,
          "value": 35902.167,
          "acquired_disposed": "D",
          "shares_owned_after": 36007.0,
          "footnote_refs": [
            "F1",
            "F4"
          ]
        }
      ]
    },
    {
      "accession": "0001526111-26-000005",
      "form": "4",
      "filed": "2026-03-20",
      "period_of_report": "2026-03-18",
      "issuer": {
        "cik": "0001045810",
        "name": "NVIDIA CORP",
        "ticker": "NVDA"
      },
      "owner": {
        "cik": "0001526111",
        "name": "Robertson Donald F Jr",
        "is_director": false,
        "is_officer": true,
        "is_10pct_owner": false,
        "is_other": false,
        "title": "Principal Accounting Officer"
      },
      "n_reporting_owners": 1,
      "doc_aff_10b5_1": true,
      "transactions": [
        {
          "security": "Common Stock",
          "date": "2026-03-18",
          "code": "F",
          "is_open_market": false,
          "is_10b5_1": true,
          "is_derivative": false,
          "shares": 4575.0,
          "price": 181.93,
          "value": 832329.75,
          "acquired_disposed": "D",
          "shares_owned_after": 342516.0,
          "footnote_refs": [
            "F1",
            "F2"
          ]
        },
        {
          "security": "Common Stock",
          "date": "2026-03-20",
          "code": "S",
          "is_open_market": true,
          "is_10b5_1": true,
          "is_derivative": false,
          "shares": 1196.0,
          "price": 172.5777,
          "value": 206402.92919999998,
          "acquired_disposed": "D",
          "shares_owned_after": 341320.0,
          "footnote_refs": [
            "F3",
            "F4"
          ]
        },
        {
          "security": "Common Stock",
          "date": "2026-03-20",
          "code": "S",
          "is_open_market": true,
          "is_10b5_1": true,
          "is_derivative": false,
          "shares": 400.0,
          "price": 172.97,
          "value": 69188.0,
          "acquired_disposed": "D",
          "shares_owned_after": 340920.0,
          "footnote_refs": [
            "F3",
            "F5"
          ]
        },
        {
          "security": "Common Stock",
          "date": "2026-03-20",
          "code": "S",
          "is_open_market": true,
          "is_10b5_1": true,
          "is_derivative": false,
          "shares": 500.0,
          "price": 173.778,
          "value": 86889.0,
          "acquired_disposed": "D",
          "shares_owned_after": 340420.0,
          "footnote_refs": [
            "F3",
            "F6"
          ]
        },
        {
          "security": "Common Stock",
          "date": "2026-03-20",
          "code": "S",
          "is_open_market": true,
          "is_10b5_1": true,
          "is_derivative": false,
          "shares": 600.0,
          "price": 174.8467,
          "value": 104908.02,
          "acquired_disposed": "D",
          "shares_owned_after": 339820.0,
          "footnote_refs": [
            "F3",
            "F7"
          ]
        },
        {
          "security": "Common Stock",
          "date": "2026-03-20",
          "code": "S",
          "is_open_market": true,
          "is_10b5_1": true,
          "is_derivative": false,
          "shares": 2100.0,
          "price": 175.7948,
          "value": 369169.08,
          "acquired_disposed": "D",
          "shares_owned_after": 337720.0,
          "footnote_refs": [
            "F3",
            "F8"
          ]
        },
        {
          "security": "Common Stock",
          "date": "2026-03-20",
          "code": "S",
          "is_open_market": true,
          "is_10b5_1": true,
          "is_derivative": false,
          "shares": 600.0,
          "price": 177.3117,
          "value": 106387.02,
          "acquired_disposed": "D",
          "shares_owned_after": 337120.0,
          "footnote_refs": [
            "F3",
            "F9"
          ]
        }
      ]
    },
    {
      "accession": "0001696841-26-000006",
      "form": "4",
      "filed": "2026-03-20",
      "period_of_report": "2026-03-18",
      "issuer": {
        "cik": "0001045810",
        "name": "NVIDIA CORP",
        "ticker": "NVDA"
      },
      "owner": {
        "cik": "0001696841",
        "name": "Teter Timothy S.",
        "is_director": false,
        "is_officer": true,
        "is_10pct_owner": false,
        "is_other": false,
        "title": "EVP, General Counsel and Sec"
      },
      "n_reporting_owners": 1,
      "doc_aff_10b5_1": false,
      "transactions": [
        {
          "security": "Common Stock",
          "date": "2026-03-18",
          "code": "F",
          "is_open_market": false,
          "is_10b5_1": false,
          "is_derivative": false,
          "shares": 66506.0,
          "price": 181.93,
          "value": 12099436.58,
          "acquired_disposed": "D",
          "shares_owned_after": 400641.0,
          "footnote_refs": [
            "F1",
            "F2",
            "F3"
          ]
        }
      ]
    },
    {
      "accession": "0001283854-26-000006",
      "form": "4",
      "filed": "2026-03-20",
      "period_of_report": "2026-03-18",
      "issuer": {
        "cik": "0001045810",
        "name": "NVIDIA CORP",
        "ticker": "NVDA"
      },
      "owner": {
        "cik": "0001283854",
        "name": "Shoquist Debora",
        "is_director": false,
        "is_officer": true,
        "is_10pct_owner": false,
        "is_other": false,
        "title": "EVP, Operations"
      },
      "n_reporting_owners": 1,
      "doc_aff_10b5_1": false,
      "transactions": [
        {
          "security": "Common Stock",
          "date": "2026-03-18",
          "code": "F",
          "is_open_market": false,
          "is_10b5_1": false,
          "is_derivative": false,
          "shares": 65140.0,
          "price": 181.93,
          "value": 11850920.200000001,
          "acquired_disposed": "D",
          "shares_owned_after": 556767.0,
          "footnote_refs": [
            "F1",
            "F2"
          ]
        }
      ]
    },
    {
      "accession": "0001347842-26-000011",
      "form": "4",
      "filed": "2026-03-20",
      "period_of_report": "2026-03-18",
      "issuer": {
        "cik": "0001045810",
        "name": "NVIDIA CORP",
        "ticker": "NVDA"
      },
      "owner": {
        "cik": "0001347842",
        "name": "Puri Ajay K",
        "is_director": false,
        "is_officer": true,
        "is_10pct_owner": false,
        "is_other": false,
        "title": "EVP, Worldwide Field Ops"
      },
      "n_reporting_owners": 1,
      "doc_aff_10b5_1": true,
      "transactions": [
        {
          "security": "Common Stock",
          "date": "2026-03-18",
          "code": "F",
          "is_open_market": false,
          "is_10b5_1": true,
          "is_derivative": false,
          "shares": 69529.0,
          "price": 181.93,
          "value": 12649410.97,
          "acquired_disposed": "D",
          "shares_owned_after": 637248.0,
          "footnote_refs": [
            "F1",
            "F2"
          ]
        },
        {
          "security": "Common Stock",
          "date": "2026-03-18",
          "code": "S",
          "is_open_market": true,
          "is_10b5_1": true,
          "is_derivative": false,
          "shares": 19881.0,
          "price": 181.312,
          "value": 3604663.8720000004,
          "acquired_disposed": "D",
          "shares_owned_after": 3298666.0,
          "footnote_refs": [
            "F3",
            "F4",
            "F5"
          ]
        },
        {
          "security": "Common Stock",
          "date": "2026-03-18",
          "code": "S",
          "is_open_market": true,
          "is_10b5_1": true,
          "is_derivative": false,
          "shares": 270134.0,
          "price": 182.2978,
          "value": 49244833.9052,
          "acquired_disposed": "D",
          "shares_owned_after": 3028532.0,
          "footnote_refs": [
            "F3",
            "F5",
            "F6"
          ]
        },
        {
          "security": "Common Stock",
          "date": "2026-03-18",
          "code": "S",
          "is_open_market": true,
          "is_10b5_1": true,
          "is_derivative": false,
          "shares": 9985.0,
          "price": 182.9386,
          "value": 1826641.921,
          "acquired_disposed": "D",
          "shares_owned_after": 3018547.0,
          "footnote_refs": [
            "F3",
            "F5",
            "F7"
          ]
        }
      ]
    },
    {
      "accession": "0001588670-26-000010",
      "form": "4",
      "filed": "2026-03-20",
      "period_of_report": "2026-03-18",
      "issuer": {
        "cik": "0001045810",
        "name": "NVIDIA CORP",
        "ticker": "NVDA"
      },
      "owner": {
        "cik": "0001588670",
        "name": "Kress Colette",
        "is_director": false,
        "is_officer": true,
        "is_10pct_owner": false,
        "is_other": false,
        "title": "EVP & Chief Financial Officer"
      },
      "n_reporting_owners": 1,
      "doc_aff_10b5_1": true,
      "transactions": [
        {
          "security": "Common",
          "date": "2026-03-18",
          "code": "F",
          "is_open_market": false,
          "is_10b5_1": true,
          "is_derivative": false,
          "shares": 76535.0,
          "price": 181.93,
          "value": 13924012.55,
          "acquired_disposed": "D",
          "shares_owned_after": 924037.0,
          "footnote_refs": [
            "F1",
            "F2"
          ]
        },
        {
          "security": "Common",
          "date": "2026-03-20",
          "code": "S",
          "is_open_market": true,
          "is_10b5_1": true,
          "is_derivative": false,
          "shares": 715.0,
          "price": 172.0119,
          "value": 122988.5085,
          "acquired_disposed": "D",
          "shares_owned_after": 923322.0,
          "footnote_refs": [
            "F3",
            "F4"
          ]
        },
        {
          "security": "Common",
          "date": "2026-03-20",
          "code": "S",
          "is_open_market": true,
          "is_10b5_1": true,
          "is_derivative": false,
          "shares": 10264.0,
          "price": 172.7096,
          "value": 1772691.3344,
          "acquired_disposed": "D",
          "shares_owned_after": 913058.0,
          "footnote_refs": [
            "F3",
            "F5"
          ]
        },
        {
          "security": "Common",
          "date": "2026-03-20",
          "code": "S",
          "is_open_market": true,
          "is_10b5_1": true,
          "is_derivative": false,
          "shares": 3307.0,
          "price": 173.6291,
          "value": 574191.4336999999,
          "acquired_disposed": "D",
          "shares_owned_after": 909751.0,
          "footnote_refs": [
            "F3",
            "F6"
          ]
        },
        {
          "security": "Common",
          "date": "2026-03-20",
          "code": "S",
          "is_open_market": true,
          "is_10b5_1": true,
          "is_derivative": false,
          "shares": 4225.0,
          "price": 174.731,
          "value": 738238.475,
          "acquired_disposed": "D",
          "shares_owned_after": 905526.0,
          "footnote_refs": [
            "F3",
            "F7"
          ]
        },
        {
          "security": "Common",
          "date": "2026-03-20",
          "code": "S",
          "is_open_market": true,
          "is_10b5_1": true,
          "is_derivative": false,
          "shares": 18020.0,
          "price": 175.7773,
          "value": 3167506.946,
          "acquired_disposed": "D",
          "shares_owned_after": 887506.0,
          "footnote_refs": [
            "F3",
            "F8"
          ]
        },
        {
          "security": "Common",
          "date": "2026-03-20",
          "code": "S",
          "is_open_market": true,
          "is_10b5_1": true,
          "is_derivative": false,
          "shares": 4212.0,
          "price": 176.8336,
          "value": 744823.1231999999,
          "acquired_disposed": "D",
          "shares_owned_after": 883294.0,
          "footnote_refs": [
            "F3",
            "F9"
          ]
        },
        {
          "security": "Common",
          "date": "2026-03-20",
          "code": "S",
          "is_open_market": true,
          "is_10b5_1": true,
          "is_derivative": false,
          "shares": 1907.0,
          "price": 177.5115,
          "value": 338514.4305,
          "acquired_disposed": "D",
          "shares_owned_after": 881387.0,
          "footnote_refs": [
            "F10",
            "F3"
          ]
        },
        {
          "security": "Common",
          "date": "2026-03-20",
          "code": "S",
          "is_open_market": true,
          "is_10b5_1": true,
          "is_derivative": false,
          "shares": 180.0,
          "price": 171.9951,
          "value": 30959.118000000002,
          "acquired_disposed": "D",
          "shares_owned_after": 92880.0,
          "footnote_refs": [
            "F3",
            "F4"
          ]
        },
        {
          "security": "Common",
          "date": "2026-03-20",
          "code": "S",
          "is_open_market": true,
          "is_10b5_1": true,
          "is_derivative": false,
          "shares": 2396.0,
          "price": 172.7091,
          "value": 413811.0036,
          "acquired_disposed": "D",
          "shares_owned_after": 90484.0,
          "footnote_refs": [
            "F3",
            "F5"
          ]
        },
        {
          "security": "Common",
          "date": "2026-03-20",
          "code": "S",
          "is_open_market": true,
          "is_10b5_1": true,
          "is_derivative": false,
          "shares": 765.0,
          "price": 173.6281,
          "value": 132825.49649999998,
          "acquired_disposed": "D",
          "shares_owned_after": 89719.0,
          "footnote_refs": [
            "F3",
            "F6"
          ]
        },
        {
          "security": "Common",
          "date": "2026-03-20",
          "code": "S",
          "is_open_market": true,
          "is_10b5_1": true,
          "is_derivative": false,
          "shares": 1051.0,
          "price": 174.7333,
          "value": 183644.69830000002,
          "acquired_disposed": "D",
          "shares_owned_after": 88668.0,
          "footnote_refs": [
            "F3",
            "F7"
          ]
        },
        {
          "security": "Common",
          "date": "2026-03-20",
          "code": "S",
          "is_open_market": true,
          "is_10b5_1": true,
          "is_derivative": false,
          "shares": 4156.0,
          "price": 175.7857,
          "value": 730565.3692,
          "acquired_disposed": "D",
          "shares_owned_after": 84512.0,
          "footnote_refs": [
            "F3",
            "F8"
          ]
        },
        {
          "security": "Common",
          "date": "2026-03-20",
          "code": "S",
          "is_open_market": true,
          "is_10b5_1": true,
          "is_derivative": false,
          "shares": 999.0,
          "price": 176.8343,
          "value": 176657.4657,
          "acquired_disposed": "D",
          "shares_owned_after": 83513.0,
          "footnote_refs": [
            "F3",
            "F9"
          ]
        },
        {
          "security": "Common",
          "date": "2026-03-20",
          "code": "S",
          "is_open_market": true,
          "is_10b5_1": true,
          "is_derivative": false,
          "shares": 453.0,
          "price": 177.5117,
          "value": 80412.8001,
          "acquired_disposed": "D",
          "shares_owned_after": 83060.0,
          "footnote_refs": [
            "F10",
            "F3"
          ]
        },
        {
          "security": "Common",
          "date": "2026-03-20",
          "code": "S",
          "is_open_market": true,
          "is_10b5_1": true,
          "is_derivative": false,
          "shares": 230.0,
          "price": 171.9681,
          "value": 39552.663,
          "acquired_disposed": "D",
          "shares_owned_after": 722704.0,
          "footnote_refs": [
            "F3",
            "F4"
          ]
        },
        {
          "security": "Common",
          "date": "2026-03-20",
          "code": "S",
          "is_open_market": true,
          "is_10b5_1": true,
          "is_derivative": false,
          "shares": 2339.0,
          "price": 172.7095,
          "value": 403967.5205,
          "acquired_disposed": "D",
          "shares_owned_after": 720365.0,
          "footnote_refs": [
            "F3",
            "F5"
          ]
        },
        {
          "security": "Common",
          "date": "2026-03-20",
          "code": "S",
          "is_open_market": true,
          "is_10b5_1": true,
          "is_derivative": false,
          "shares": 734.0,
          "price": 173.6275,
          "value": 127442.58499999999,
          "acquired_disposed": "D",
          "shares_owned_after": 719631.0,
          "footnote_refs": [
            "F3",
            "F6"
          ]
        },
        {
          "security": "Common",
          "date": "2026-03-20",
          "code": "S",
          "is_open_market": true,
          "is_10b5_1": true,
          "is_derivative": false,
          "shares": 1316.0,
          "price": 174.7468,
          "value": 229966.7888,
          "acquired_disposed": "D",
          "shares_owned_after": 718315.0,
          "footnote_refs": [
            "F3",
            "F7"
          ]
        },
        {
          "security": "Common",
          "date": "2026-03-20",
          "code": "S",
          "is_open_market": true,
          "is_10b5_1": true,
          "is_derivative": false,
          "shares": 3876.0,
          "price": 175.8248,
          "value": 681496.9248,
          "acquired_disposed": "D",
          "shares_owned_after": 714439.0,
          "footnote_refs": [
            "F3",
            "F8"
          ]
        },
        {
          "security": "Common",
          "date": "2026-03-20",
          "code": "S",
          "is_open_market": true,
          "is_10b5_1": true,
          "is_derivative": false,
          "shares": 1034.0,
          "price": 176.8288,
          "value": 182840.9792,
          "acquired_disposed": "D",
          "shares_owned_after": 713405.0,
          "footnote_refs": [
            "F3",
            "F9"
          ]
        },
        {
          "security": "Common",
          "date": "2026-03-20",
          "code": "S",
          "is_open_market": true,
          "is_10b5_1": true,
          "is_derivative": false,
          "shares": 471.0,
          "price": 177.5122,
          "value": 83608.24620000001,
          "acquired_disposed": "D",
          "shares_owned_after": 712934.0,
          "footnote_refs": [
            "F10",
            "F3"
          ]
        }
      ]
    },
    {
      "accession": "0001197649-26-000005",
      "form": "4",
      "filed": "2026-03-20",
      "period_of_report": "2026-03-18",
      "issuer": {
        "cik": "0001045810",
        "name": "NVIDIA CORP",
        "ticker": "NVDA"
      },
      "owner": {
        "cik": "0001197649",
        "name": "HUANG JEN HSUN",
        "is_director": true,
        "is_officer": true,
        "is_10pct_owner": false,
        "is_other": false,
        "title": "President and CEO"
      },
      "n_reporting_owners": 1,
      "doc_aff_10b5_1": false,
      "transactions": [
        {
          "security": "Common Stock",
          "date": "2026-03-18",
          "code": "F",
          "is_open_market": false,
          "is_10b5_1": false,
          "is_derivative": false,
          "shares": 437908.0,
          "price": 181.93,
          "value": 79668602.44,
          "acquired_disposed": "D",
          "shares_owned_after": 70191975.0,
          "footnote_refs": [
            "F1",
            "F2"
          ]
        },
        {
          "security": "Common Stock",
          "date": "2026-03-18",
          "code": "G",
          "is_open_market": false,
          "is_10b5_1": false,
          "is_derivative": false,
          "shares": 29481301.0,
          "price": 0.0,
          "value": 0.0,
          "acquired_disposed": "D",
          "shares_owned_after": 0.0,
          "footnote_refs": [
            "F3",
            "F4"
          ]
        },
        {
          "security": "Common Stock",
          "date": "2026-03-18",
          "code": "G",
          "is_open_market": false,
          "is_10b5_1": false,
          "is_derivative": false,
          "shares": 29481301.0,
          "price": 0.0,
          "value": 0.0,
          "acquired_disposed": "D",
          "shares_owned_after": 0.0,
          "footnote_refs": [
            "F5",
            "F6"
          ]
        },
        {
          "security": "Common Stock",
          "date": "2026-03-18",
          "code": "G",
          "is_open_market": false,
          "is_10b5_1": false,
          "is_derivative": false,
          "shares": 58962602.0,
          "price": 0.0,
          "value": 0.0,
          "acquired_disposed": "A",
          "shares_owned_after": 109040602.0,
          "footnote_refs": [
            "F3",
            "F5"
          ]
        }
      ]
    },
    {
      "accession": "0001197652-26-000003",
      "form": "4",
      "filed": "2026-03-19",
      "period_of_report": "2026-03-17",
      "issuer": {
        "cik": "0001045810",
        "name": "NVIDIA CORP",
        "ticker": "NVDA"
      },
      "owner": {
        "cik": "0001197652",
        "name": "SEAWELL A BROOKE",
        "is_director": true,
        "is_officer": false,
        "is_10pct_owner": false,
        "is_other": false,
        "title": null
      },
      "n_reporting_owners": 1,
      "doc_aff_10b5_1": false,
      "transactions": [
        {
          "security": "Common Stock",
          "date": "2026-03-17",
          "code": "G",
          "is_open_market": false,
          "is_10b5_1": false,
          "is_derivative": false,
          "shares": 530.0,
          "price": 0.0,
          "value": 0.0,
          "acquired_disposed": "D",
          "shares_owned_after": 6607.0,
          "footnote_refs": [
            "F1"
          ]
        }
      ]
    },
    {
      "accession": "0001818224-26-000002",
      "form": "4",
      "filed": "2026-03-17",
      "period_of_report": "2026-03-13",
      "issuer": {
        "cik": "0001045810",
        "name": "NVIDIA CORP",
        "ticker": "NVDA"
      },
      "owner": {
        "cik": "0001818224",
        "name": "Dabiri John",
        "is_director": true,
        "is_officer": false,
        "is_10pct_owner": false,
        "is_other": false,
        "title": null
      },
      "n_reporting_owners": 1,
      "doc_aff_10b5_1": true,
      "transactions": [
        {
          "security": "Common",
          "date": "2026-03-13",
          "code": "S",
          "is_open_market": true,
          "is_10b5_1": true,
          "is_derivative": false,
          "shares": 3004.0,
          "price": 184.9,
          "value": 555439.6,
          "acquired_disposed": "D",
          "shares_owned_after": 14788.0,
          "footnote_refs": [
            "F1"
          ]
        }
      ]
    },
    {
      "accession": "0001696841-26-000004",
      "form": "4",
      "filed": "2026-03-11",
      "period_of_report": "2026-03-09",
      "issuer": {
        "cik": "0001045810",
        "name": "NVIDIA CORP",
        "ticker": "NVDA"
      },
      "owner": {
        "cik": "0001696841",
        "name": "Teter Timothy S.",
        "is_director": false,
        "is_officer": true,
        "is_10pct_owner": false,
        "is_other": false,
        "title": "EVP, General Counsel and Sec"
      },
      "n_reporting_owners": 1,
      "doc_aff_10b5_1": false,
      "transactions": [
        {
          "security": "Common Stock",
          "date": "2026-03-09",
          "code": "A",
          "is_open_market": false,
          "is_10b5_1": false,
          "is_derivative": false,
          "shares": 47048.0,
          "price": 0.0,
          "value": 0.0,
          "acquired_disposed": "A",
          "shares_owned_after": 524795.0,
          "footnote_refs": [
            "F1",
            "F2"
          ]
        }
      ]
    },
    {
      "accession": "0001283854-26-000004",
      "form": "4",
      "filed": "2026-03-11",
      "period_of_report": "2026-03-09",
      "issuer": {
        "cik": "0001045810",
        "name": "NVIDIA CORP",
        "ticker": "NVDA"
      },
      "owner": {
        "cik": "0001283854",
        "name": "Shoquist Debora",
        "is_director": false,
        "is_officer": true,
        "is_10pct_owner": false,
        "is_other": false,
        "title": "EVP, Operations"
      },
      "n_reporting_owners": 1,
      "doc_aff_10b5_1": false,
      "transactions": [
        {
          "security": "Common Stock",
          "date": "2026-03-09",
          "code": "A",
          "is_open_market": false,
          "is_10b5_1": false,
          "is_derivative": false,
          "shares": 47048.0,
          "price": 0.0,
          "value": 0.0,
          "acquired_disposed": "A",
          "shares_owned_after": 621907.0,
          "footnote_refs": [
            "F1",
            "F2"
          ]
        }
      ]
    },
    {
      "accession": "0001588670-26-000008",
      "form": "4",
      "filed": "2026-03-11",
      "period_of_report": "2026-03-09",
      "issuer": {
        "cik": "0001045810",
        "name": "NVIDIA CORP",
        "ticker": "NVDA"
      },
      "owner": {
        "cik": "0001588670",
        "name": "Kress Colette",
        "is_director": false,
        "is_officer": true,
        "is_10pct_owner": false,
        "is_other": false,
        "title": "EVP & Chief Financial Officer"
      },
      "n_reporting_owners": 1,
      "doc_aff_10b5_1": false,
      "transactions": [
        {
          "security": "Common",
          "date": "2026-03-09",
          "code": "A",
          "is_open_market": false,
          "is_10b5_1": false,
          "is_derivative": false,
          "shares": 47048.0,
          "price": 0.0,
          "value": 0.0,
          "acquired_disposed": "A",
          "shares_owned_after": 1000572.0,
          "footnote_refs": [
            "F1",
            "F2"
          ]
        }
      ]
    },
    {
      "accession": "0001347842-26-000009",
      "form": "4",
      "filed": "2026-03-11",
      "period_of_report": "2026-03-09",
      "issuer": {
        "cik": "0001045810",
        "name": "NVIDIA CORP",
        "ticker": "NVDA"
      },
      "owner": {
        "cik": "0001347842",
        "name": "Puri Ajay K",
        "is_director": false,
        "is_officer": true,
        "is_10pct_owner": false,
        "is_other": false,
        "title": "EVP, Worldwide Field Ops"
      },
      "n_reporting_owners": 1,
      "doc_aff_10b5_1": true,
      "transactions": [
        {
          "security": "Common Stock",
          "date": "2026-03-09",
          "code": "A",
          "is_open_market": false,
          "is_10b5_1": true,
          "is_derivative": false,
          "shares": 47048.0,
          "price": 0.0,
          "value": 0.0,
          "acquired_disposed": "A",
          "shares_owned_after": 706777.0,
          "footnote_refs": [
            "F1",
            "F2"
          ]
        },
        {
          "security": "Common Stock",
          "date": "2026-03-10",
          "code": "S",
          "is_open_market": true,
          "is_10b5_1": true,
          "is_derivative": false,
          "shares": 275060.0,
          "price": 182.4663,
          "value": 50189180.478,
          "acquired_disposed": "D",
          "shares_owned_after": 3343487.0,
          "footnote_refs": [
            "F3",
            "F4",
            "F5"
          ]
        },
        {
          "security": "Common Stock",
          "date": "2026-03-10",
          "code": "S",
          "is_open_market": true,
          "is_10b5_1": true,
          "is_derivative": false,
          "shares": 24940.0,
          "price": 183.114,
          "value": 4566863.16,
          "acquired_disposed": "D",
          "shares_owned_after": 3318547.0,
          "footnote_refs": [
            "F3",
            "F5",
            "F6"
          ]
        }
      ]
    },
    {
      "accession": "0001347842-26-000007",
      "form": "4",
      "filed": "2026-03-04",
      "period_of_report": "2026-03-02",
      "issuer": {
        "cik": "0001045810",
        "name": "NVIDIA CORP",
        "ticker": "NVDA"
      },
      "owner": {
        "cik": "0001347842",
        "name": "Puri Ajay K",
        "is_director": false,
        "is_officer": true,
        "is_10pct_owner": false,
        "is_other": false,
        "title": "EVP, Worldwide Field Ops"
      },
      "n_reporting_owners": 1,
      "doc_aff_10b5_1": false,
      "transactions": [
        {
          "security": "Common Stock",
          "date": "2026-03-02",
          "code": "A",
          "is_open_market": false,
          "is_10b5_1": false,
          "is_derivative": false,
          "shares": 55558.0,
          "price": 0.0,
          "value": 0.0,
          "acquired_disposed": "A",
          "shares_owned_after": 612009.0,
          "footnote_refs": [
            "F1",
            "F2",
            "F3"
          ]
        },
        {
          "security": "Common Stock",
          "date": "2026-03-02",
          "code": "A",
          "is_open_market": false,
          "is_10b5_1": false,
          "is_derivative": false,
          "shares": 47720.0,
          "price": 0.0,
          "value": 0.0,
          "acquired_disposed": "A",
          "shares_owned_after": 659729.0,
          "footnote_refs": [
            "F2",
            "F4"
          ]
        }
      ]
    },
    {
      "accession": "0001283854-26-000002",
      "form": "4",
      "filed": "2026-03-04",
      "period_of_report": "2026-03-02",
      "issuer": {
        "cik": "0001045810",
        "name": "NVIDIA CORP",
        "ticker": "NVDA"
      },
      "owner": {
        "cik": "0001283854",
        "name": "Shoquist Debora",
        "is_director": false,
        "is_officer": true,
        "is_10pct_owner": false,
        "is_other": false,
        "title": "EVP, Operations"
      },
      "n_reporting_owners": 1,
      "doc_aff_10b5_1": false,
      "transactions": [
        {
          "security": "Common Stock",
          "date": "2026-03-02",
          "code": "A",
          "is_open_market": false,
          "is_10b5_1": false,
          "is_derivative": false,
          "shares": 57488.0,
          "price": 0.0,
          "value": 0.0,
          "acquired_disposed": "A",
          "shares_owned_after": 534019.0,
          "footnote_refs": [
            "F1",
            "F2",
            "F3"
          ]
        },
        {
          "security": "Common Stock",
          "date": "2026-03-02",
          "code": "A",
          "is_open_market": false,
          "is_10b5_1": false,
          "is_derivative": false,
          "shares": 40840.0,
          "price": 0.0,
          "value": 0.0,
          "acquired_disposed": "A",
          "shares_owned_after": 574859.0,
          "footnote_refs": [
            "F2",
            "F4"
          ]
        }
      ]
    },
    {
      "accession": "0001588670-26-000006",
      "form": "4",
      "filed": "2026-03-04",
      "period_of_report": "2026-03-02",
      "issuer": {
        "cik": "0001045810",
        "name": "NVIDIA CORP",
        "ticker": "NVDA"
      },
      "owner": {
        "cik": "0001588670",
        "name": "Kress Colette",
        "is_director": false,
        "is_officer": true,
        "is_10pct_owner": false,
        "is_other": false,
        "title": "EVP & Chief Financial Officer"
      },
      "n_reporting_owners": 1,
      "doc_aff_10b5_1": false,
      "transactions": [
        {
          "security": "Common",
          "date": "2026-03-02",
          "code": "A",
          "is_open_market": false,
          "is_10b5_1": false,
          "is_derivative": false,
          "shares": 57100.0,
          "price": 0.0,
          "value": 0.0,
          "acquired_disposed": "A",
          "shares_owned_after": 903964.0,
          "footnote_refs": [
            "F1",
            "F2",
            "F3"
          ]
        },
        {
          "security": "Common",
          "date": "2026-03-02",
          "code": "A",
          "is_open_market": false,
          "is_10b5_1": false,
          "is_derivative": false,
          "shares": 49560.0,
          "price": 0.0,
          "value": 0.0,
          "acquired_disposed": "A",
          "shares_owned_after": 953524.0,
          "footnote_refs": [
            "F2",
            "F4"
          ]
        }
      ]
    },
    {
      "accession": "0001696841-26-000002",
      "form": "4",
      "filed": "2026-03-04",
      "period_of_report": "2026-03-02",
      "issuer": {
        "cik": "0001045810",
        "name": "NVIDIA CORP",
        "ticker": "NVDA"
      },
      "owner": {
        "cik": "0001696841",
        "name": "Teter Timothy S.",
        "is_director": false,
        "is_officer": true,
        "is_10pct_owner": false,
        "is_other": false,
        "title": "EVP, General Counsel and Sec"
      },
      "n_reporting_owners": 1,
      "doc_aff_10b5_1": false,
      "transactions": [
        {
          "security": "Common Stock",
          "date": "2026-03-02",
          "code": "A",
          "is_open_market": false,
          "is_10b5_1": false,
          "is_derivative": false,
          "shares": 57488.0,
          "price": 0.0,
          "value": 0.0,
          "acquired_disposed": "A",
          "shares_owned_after": 436907.0,
          "footnote_refs": [
            "F1",
            "F2",
            "F3"
          ]
        },
        {
          "security": "Common Stock",
          "date": "2026-03-02",
          "code": "A",
          "is_open_market": false,
          "is_10b5_1": false,
          "is_derivative": false,
          "shares": 40840.0,
          "price": 0.0,
          "value": 0.0,
          "acquired_disposed": "A",
          "shares_owned_after": 477747.0,
          "footnote_refs": [
            "F2",
            "F4"
          ]
        }
      ]
    },
    {
      "accession": "0001197649-26-000003",
      "form": "4",
      "filed": "2026-03-04",
      "period_of_report": "2026-03-02",
      "issuer": {
        "cik": "0001045810",
        "name": "NVIDIA CORP",
        "ticker": "NVDA"
      },
      "owner": {
        "cik": "0001197649",
        "name": "HUANG JEN HSUN",
        "is_director": true,
        "is_officer": true,
        "is_10pct_owner": false,
        "is_other": false,
        "title": "President and CEO"
      },
      "n_reporting_owners": 1,
      "doc_aff_10b5_1": false,
      "transactions": [
        {
          "security": "Common Stock",
          "date": "2026-03-02",
          "code": "A",
          "is_open_market": false,
          "is_10b5_1": false,
          "is_derivative": false,
          "shares": 179411.0,
          "price": 0.0,
          "value": 0.0,
          "acquired_disposed": "A",
          "shares_owned_after": 69872523.0,
          "footnote_refs": [
            "F1",
            "F2",
            "F3"
          ]
        },
        {
          "security": "Common Stock",
          "date": "2026-03-02",
          "code": "A",
          "is_open_market": false,
          "is_10b5_1": false,
          "is_derivative": false,
          "shares": 757360.0,
          "price": 0.0,
          "value": 0.0,
          "acquired_disposed": "A",
          "shares_owned_after": 70629883.0,
          "footnote_refs": [
            "F2",
            "F4"
          ]
        }
      ]
    }
  ]
}