{
  "runs": [
    {
      "updated": "2026-05-25T23:35:31Z",
      "n_experiments": 60,
      "n_candidates": 0,
      "funnel": {
        "raw_significant": 53,
        "after_fdr": 53,
        "after_holdout": 0
      }
    },
    {
      "updated": "2026-06-05T10:23:47Z",
      "n_experiments": 60,
      "n_candidates": 0,
      "funnel": {
        "raw_significant": 40,
        "after_fdr": 40,
        "after_holdout": 0
      }
    },
    {
      "updated": "2026-06-05T10:42:52Z",
      "n_experiments": 60,
      "n_candidates": 0,
      "funnel": {
        "raw_significant": 40,
        "after_fdr": 40,
        "after_holdout": 0
      }
    },
    {
      "updated": "2026-06-05T11:05:09Z",
      "n_experiments": 60,
      "n_candidates": 0,
      "funnel": {
        "raw_significant": 40,
        "after_fdr": 40,
        "after_holdout": 0
      }
    },
    {
      "updated": "2026-06-05T14:13:41Z",
      "n_experiments": 60,
      "n_candidates": 0,
      "funnel": {
        "raw_significant": 40,
        "after_fdr": 40,
        "after_holdout": 0
      }
    },
    {
      "updated": "2026-06-05T16:53:38Z",
      "n_experiments": 60,
      "n_candidates": 0,
      "funnel": {
        "raw_significant": 40,
        "after_fdr": 40,
        "after_holdout": 0
      }
    },
    {
      "updated": "2026-06-05T19:22:36Z",
      "n_experiments": 60,
      "n_candidates": 0,
      "funnel": {
        "raw_significant": 40,
        "after_fdr": 40,
        "after_holdout": 0
      }
    },
    {
      "updated": "2026-06-05T21:09:42Z",
      "n_experiments": 60,
      "n_candidates": 0,
      "funnel": {
        "raw_significant": 40,
        "after_fdr": 40,
        "after_holdout": 0
      }
    },
    {
      "updated": "2026-06-05T22:46:55Z",
      "n_experiments": 60,
      "n_candidates": 0,
      "funnel": {
        "raw_significant": 40,
        "after_fdr": 40,
        "after_holdout": 0
      }
    },
    {
      "updated": "2026-06-06T01:35:53Z",
      "n_experiments": 60,
      "n_candidates": 0,
      "funnel": {
        "raw_significant": 40,
        "after_fdr": 40,
        "after_holdout": 0
      }
    },
    {
      "updated": "2026-06-06T06:14:17Z",
      "n_experiments": 60,
      "n_candidates": 0,
      "funnel": {
        "raw_significant": 40,
        "after_fdr": 40,
        "after_holdout": 0
      }
    },
    {
      "updated": "2026-06-06T09:14:22Z",
      "n_experiments": 60,
      "n_candidates": 0,
      "funnel": {
        "raw_significant": 40,
        "after_fdr": 40,
        "after_holdout": 0
      }
    },
    {
      "updated": "2026-06-06T09:39:27Z",
      "n_experiments": 60,
      "n_candidates": 0,
      "funnel": {
        "raw_significant": 40,
        "after_fdr": 40,
        "after_holdout": 0
      }
    },
    {
      "updated": "2026-06-06T11:10:00Z",
      "n_experiments": 60,
      "n_candidates": 0,
      "funnel": {
        "raw_significant": 40,
        "after_fdr": 40,
        "after_holdout": 0
      }
    },
    {
      "updated": "2026-06-06T12:58:50Z",
      "n_experiments": 60,
      "n_candidates": 0,
      "funnel": {
        "raw_significant": 40,
        "after_fdr": 40,
        "after_holdout": 0
      }
    },
    {
      "updated": "2026-06-06T15:04:23Z",
      "n_experiments": 60,
      "n_candidates": 0,
      "funnel": {
        "raw_significant": 40,
        "after_fdr": 40,
        "after_holdout": 0
      }
    },
    {
      "updated": "2026-06-06T16:46:09Z",
      "n_experiments": 60,
      "n_candidates": 0,
      "funnel": {
        "raw_significant": 40,
        "after_fdr": 40,
        "after_holdout": 0
      }
    },
    {
      "updated": "2026-06-06T18:53:02Z",
      "n_experiments": 60,
      "n_candidates": 0,
      "funnel": {
        "raw_significant": 40,
        "after_fdr": 40,
        "after_holdout": 0
      }
    },
    {
      "updated": "2026-06-06T20:46:54Z",
      "n_experiments": 60,
      "n_candidates": 0,
      "funnel": {
        "raw_significant": 40,
        "after_fdr": 40,
        "after_holdout": 0
      }
    },
    {
      "updated": "2026-06-06T22:42:56Z",
      "n_experiments": 60,
      "n_candidates": 0,
      "funnel": {
        "raw_significant": 40,
        "after_fdr": 40,
        "after_holdout": 0
      }
    },
    {
      "updated": "2026-06-07T01:44:36Z",
      "n_experiments": 60,
      "n_candidates": 0,
      "funnel": {
        "raw_significant": 40,
        "after_fdr": 40,
        "after_holdout": 0
      }
    },
    {
      "updated": "2026-06-07T06:54:02Z",
      "n_experiments": 60,
      "n_candidates": 0,
      "funnel": {
        "raw_significant": 40,
        "after_fdr": 40,
        "after_holdout": 0
      }
    },
    {
      "updated": "2026-06-07T10:20:31Z",
      "n_experiments": 60,
      "n_candidates": 0,
      "funnel": {
        "raw_significant": 40,
        "after_fdr": 40,
        "after_holdout": 0
      }
    },
    {
      "updated": "2026-06-07T12:13:06Z",
      "n_experiments": 60,
      "n_candidates": 0,
      "funnel": {
        "raw_significant": 40,
        "after_fdr": 40,
        "after_holdout": 0
      }
    },
    {
      "updated": "2026-06-07T14:33:13Z",
      "n_experiments": 60,
      "n_candidates": 0,
      "funnel": {
        "raw_significant": 40,
        "after_fdr": 40,
        "after_holdout": 0
      }
    },
    {
      "updated": "2026-06-07T16:57:00Z",
      "n_experiments": 60,
      "n_candidates": 0,
      "funnel": {
        "raw_significant": 40,
        "after_fdr": 40,
        "after_holdout": 0
      }
    },
    {
      "updated": "2026-06-07T18:52:20Z",
      "n_experiments": 60,
      "n_candidates": 0,
      "funnel": {
        "raw_significant": 40,
        "after_fdr": 40,
        "after_holdout": 0
      }
    },
    {
      "updated": "2026-06-07T20:50:00Z",
      "n_experiments": 60,
      "n_candidates": 0,
      "funnel": {
        "raw_significant": 40,
        "after_fdr": 40,
        "after_holdout": 0
      }
    },
    {
      "updated": "2026-06-07T22:41:32Z",
      "n_experiments": 60,
      "n_candidates": 0,
      "funnel": {
        "raw_significant": 40,
        "after_fdr": 40,
        "after_holdout": 0
      }
    },
    {
      "updated": "2026-06-08T01:46:08Z",
      "n_experiments": 60,
      "n_candidates": 0,
      "funnel": {
        "raw_significant": 40,
        "after_fdr": 40,
        "after_holdout": 0
      }
    },
    {
      "updated": "2026-06-08T07:19:04Z",
      "n_experiments": 60,
      "n_candidates": 0,
      "funnel": {
        "raw_significant": 40,
        "after_fdr": 40,
        "after_holdout": 0
      }
    },
    {
      "updated": "2026-06-08T12:20:36Z",
      "n_experiments": 60,
      "n_candidates": 0,
      "funnel": {
        "raw_significant": 40,
        "after_fdr": 40,
        "after_holdout": 0
      }
    },
    {
      "updated": "2026-06-08T16:41:27Z",
      "n_experiments": 60,
      "n_candidates": 0,
      "funnel": {
        "raw_significant": 40,
        "after_fdr": 40,
        "after_holdout": 0
      }
    },
    {
      "updated": "2026-06-08T19:46:43Z",
      "n_experiments": 60,
      "n_candidates": 0,
      "funnel": {
        "raw_significant": 40,
        "after_fdr": 40,
        "after_holdout": 0
      }
    },
    {
      "updated": "2026-06-08T22:14:33Z",
      "n_experiments": 60,
      "n_candidates": 0,
      "funnel": {
        "raw_significant": 40,
        "after_fdr": 40,
        "after_holdout": 0
      }
    },
    {
      "updated": "2026-06-08T23:02:27Z",
      "n_experiments": 60,
      "n_candidates": 0,
      "funnel": {
        "raw_significant": 40,
        "after_fdr": 40,
        "after_holdout": 0
      }
    },
    {
      "updated": "2026-06-08T23:51:16Z",
      "n_experiments": 60,
      "n_candidates": 0,
      "funnel": {
        "raw_significant": 40,
        "after_fdr": 40,
        "after_holdout": 0
      }
    },
    {
      "updated": "2026-06-09T04:50:36Z",
      "n_experiments": 60,
      "n_candidates": 0,
      "funnel": {
        "raw_significant": 40,
        "after_fdr": 40,
        "after_holdout": 0
      }
    },
    {
      "updated": "2026-06-09T08:53:02Z",
      "n_experiments": 60,
      "n_candidates": 0,
      "funnel": {
        "raw_significant": 40,
        "after_fdr": 40,
        "after_holdout": 0
      }
    },
    {
      "updated": "2026-06-09T10:50:14Z",
      "n_experiments": 60,
      "n_candidates": 0,
      "funnel": {
        "raw_significant": 40,
        "after_fdr": 40,
        "after_holdout": 0
      }
    },
    {
      "updated": "2026-06-09T12:27:57Z",
      "n_experiments": 60,
      "n_candidates": 0,
      "funnel": {
        "raw_significant": 40,
        "after_fdr": 40,
        "after_holdout": 0
      }
    },
    {
      "updated": "2026-06-09T15:40:05Z",
      "n_experiments": 60,
      "n_candidates": 0,
      "funnel": {
        "raw_significant": 41,
        "after_fdr": 40,
        "after_holdout": 0
      }
    },
    {
      "updated": "2026-06-09T18:35:14Z",
      "n_experiments": 60,
      "n_candidates": 0,
      "funnel": {
        "raw_significant": 41,
        "after_fdr": 40,
        "after_holdout": 0
      }
    },
    {
      "updated": "2026-06-09T21:24:18Z",
      "n_experiments": 60,
      "n_candidates": 0,
      "funnel": {
        "raw_significant": 41,
        "after_fdr": 40,
        "after_holdout": 0
      }
    },
    {
      "updated": "2026-06-09T23:04:05Z",
      "n_experiments": 60,
      "n_candidates": 0,
      "funnel": {
        "raw_significant": 41,
        "after_fdr": 40,
        "after_holdout": 0
      }
    },
    {
      "updated": "2026-06-10T01:43:59Z",
      "n_experiments": 60,
      "n_candidates": 0,
      "funnel": {
        "raw_significant": 41,
        "after_fdr": 40,
        "after_holdout": 0
      }
    },
    {
      "updated": "2026-06-10T06:55:11Z",
      "n_experiments": 60,
      "n_candidates": 0,
      "funnel": {
        "raw_significant": 41,
        "after_fdr": 40,
        "after_holdout": 0
      }
    },
    {
      "updated": "2026-06-10T11:15:44Z",
      "n_experiments": 60,
      "n_candidates": 0,
      "funnel": {
        "raw_significant": 41,
        "after_fdr": 40,
        "after_holdout": 0
      }
    },
    {
      "updated": "2026-06-10T14:41:20Z",
      "n_experiments": 60,
      "n_candidates": 41,
      "funnel": {
        "raw_significant": 41,
        "after_fdr": 41,
        "after_holdout": 41
      }
    },
    {
      "updated": "2026-06-10T18:21:33Z",
      "n_experiments": 60,
      "n_candidates": 41,
      "funnel": {
        "raw_significant": 41,
        "after_fdr": 41,
        "after_holdout": 41
      }
    },
    {
      "updated": "2026-06-10T21:13:22Z",
      "n_experiments": 60,
      "n_candidates": 41,
      "funnel": {
        "raw_significant": 41,
        "after_fdr": 41,
        "after_holdout": 41
      }
    },
    {
      "updated": "2026-06-10T23:14:57Z",
      "n_experiments": 60,
      "n_candidates": 41,
      "funnel": {
        "raw_significant": 41,
        "after_fdr": 41,
        "after_holdout": 41
      }
    },
    {
      "updated": "2026-06-11T01:53:10Z",
      "n_experiments": 60,
      "n_candidates": 41,
      "funnel": {
        "raw_significant": 41,
        "after_fdr": 41,
        "after_holdout": 41
      }
    },
    {
      "updated": "2026-06-11T07:21:00Z",
      "n_experiments": 60,
      "n_candidates": 41,
      "funnel": {
        "raw_significant": 41,
        "after_fdr": 41,
        "after_holdout": 41
      }
    },
    {
      "updated": "2026-06-11T12:00:58Z",
      "n_experiments": 60,
      "n_candidates": 41,
      "funnel": {
        "raw_significant": 41,
        "after_fdr": 41,
        "after_holdout": 41
      }
    },
    {
      "updated": "2026-06-11T16:42:26Z",
      "n_experiments": 60,
      "n_candidates": 41,
      "funnel": {
        "raw_significant": 41,
        "after_fdr": 41,
        "after_holdout": 41
      }
    },
    {
      "updated": "2026-06-11T20:05:50Z",
      "n_experiments": 60,
      "n_candidates": 41,
      "funnel": {
        "raw_significant": 41,
        "after_fdr": 41,
        "after_holdout": 41
      }
    },
    {
      "updated": "2026-06-11T22:29:53Z",
      "n_experiments": 60,
      "n_candidates": 41,
      "funnel": {
        "raw_significant": 41,
        "after_fdr": 41,
        "after_holdout": 41
      }
    },
    {
      "updated": "2026-06-11T23:12:57Z",
      "n_experiments": 60,
      "n_candidates": 41,
      "funnel": {
        "raw_significant": 41,
        "after_fdr": 41,
        "after_holdout": 41
      }
    },
    {
      "updated": "2026-06-12T00:07:19Z",
      "n_experiments": 60,
      "n_candidates": 41,
      "funnel": {
        "raw_significant": 41,
        "after_fdr": 41,
        "after_holdout": 41
      }
    },
    {
      "updated": "2026-06-12T05:20:03Z",
      "n_experiments": 60,
      "n_candidates": 41,
      "funnel": {
        "raw_significant": 41,
        "after_fdr": 41,
        "after_holdout": 41
      }
    },
    {
      "updated": "2026-06-12T09:25:37Z",
      "n_experiments": 60,
      "n_candidates": 41,
      "funnel": {
        "raw_significant": 41,
        "after_fdr": 41,
        "after_holdout": 41
      }
    },
    {
      "updated": "2026-06-12T11:17:50Z",
      "n_experiments": 60,
      "n_candidates": 41,
      "funnel": {
        "raw_significant": 41,
        "after_fdr": 41,
        "after_holdout": 41
      }
    },
    {
      "updated": "2026-06-12T12:46:43Z",
      "n_experiments": 60,
      "n_candidates": 41,
      "funnel": {
        "raw_significant": 41,
        "after_fdr": 41,
        "after_holdout": 41
      }
    },
    {
      "updated": "2026-06-12T16:39:57Z",
      "n_experiments": 60,
      "n_candidates": 0,
      "funnel": {
        "raw_significant": 43,
        "after_fdr": 42,
        "after_holdout": 0
      }
    },
    {
      "updated": "2026-06-12T19:36:05Z",
      "n_experiments": 60,
      "n_candidates": 0,
      "funnel": {
        "raw_significant": 43,
        "after_fdr": 42,
        "after_holdout": 0
      }
    },
    {
      "updated": "2026-06-12T22:12:34Z",
      "n_experiments": 60,
      "n_candidates": 0,
      "funnel": {
        "raw_significant": 43,
        "after_fdr": 42,
        "after_holdout": 0
      }
    },
    {
      "updated": "2026-06-12T23:03:25Z",
      "n_experiments": 60,
      "n_candidates": 0,
      "funnel": {
        "raw_significant": 43,
        "after_fdr": 42,
        "after_holdout": 0
      }
    },
    {
      "updated": "2026-06-13T00:06:23Z",
      "n_experiments": 60,
      "n_candidates": 0,
      "funnel": {
        "raw_significant": 43,
        "after_fdr": 42,
        "after_holdout": 0
      }
    },
    {
      "updated": "2026-06-13T05:05:32Z",
      "n_experiments": 60,
      "n_candidates": 0,
      "funnel": {
        "raw_significant": 43,
        "after_fdr": 42,
        "after_holdout": 0
      }
    },
    {
      "updated": "2026-06-13T08:44:07Z",
      "n_experiments": 60,
      "n_candidates": 0,
      "funnel": {
        "raw_significant": 43,
        "after_fdr": 42,
        "after_holdout": 0
      }
    },
    {
      "updated": "2026-06-13T10:17:25Z",
      "n_experiments": 60,
      "n_candidates": 0,
      "funnel": {
        "raw_significant": 43,
        "after_fdr": 42,
        "after_holdout": 0
      }
    },
    {
      "updated": "2026-06-13T11:36:19Z",
      "n_experiments": 60,
      "n_candidates": 0,
      "funnel": {
        "raw_significant": 43,
        "after_fdr": 42,
        "after_holdout": 0
      }
    },
    {
      "updated": "2026-06-13T14:42:26Z",
      "n_experiments": 60,
      "n_candidates": 0,
      "funnel": {
        "raw_significant": 43,
        "after_fdr": 42,
        "after_holdout": 0
      }
    },
    {
      "updated": "2026-06-13T17:02:39Z",
      "n_experiments": 60,
      "n_candidates": 0,
      "funnel": {
        "raw_significant": 43,
        "after_fdr": 42,
        "after_holdout": 0
      }
    },
    {
      "updated": "2026-06-13T18:59:30Z",
      "n_experiments": 60,
      "n_candidates": 0,
      "funnel": {
        "raw_significant": 43,
        "after_fdr": 42,
        "after_holdout": 0
      }
    },
    {
      "updated": "2026-06-13T20:53:34Z",
      "n_experiments": 60,
      "n_candidates": 0,
      "funnel": {
        "raw_significant": 43,
        "after_fdr": 42,
        "after_holdout": 0
      }
    },
    {
      "updated": "2026-06-13T22:43:52Z",
      "n_experiments": 60,
      "n_candidates": 0,
      "funnel": {
        "raw_significant": 43,
        "after_fdr": 42,
        "after_holdout": 0
      }
    },
    {
      "updated": "2026-06-14T01:49:35Z",
      "n_experiments": 60,
      "n_candidates": 0,
      "funnel": {
        "raw_significant": 43,
        "after_fdr": 42,
        "after_holdout": 0
      }
    },
    {
      "updated": "2026-06-14T07:10:43Z",
      "n_experiments": 60,
      "n_candidates": 0,
      "funnel": {
        "raw_significant": 43,
        "after_fdr": 42,
        "after_holdout": 0
      }
    },
    {
      "updated": "2026-06-14T10:43:55Z",
      "n_experiments": 60,
      "n_candidates": 0,
      "funnel": {
        "raw_significant": 43,
        "after_fdr": 42,
        "after_holdout": 0
      }
    },
    {
      "updated": "2026-06-14T13:19:08Z",
      "n_experiments": 60,
      "n_candidates": 0,
      "funnel": {
        "raw_significant": 43,
        "after_fdr": 42,
        "after_holdout": 0
      }
    },
    {
      "updated": "2026-06-14T15:31:59Z",
      "n_experiments": 60,
      "n_candidates": 0,
      "funnel": {
        "raw_significant": 43,
        "after_fdr": 42,
        "after_holdout": 0
      }
    },
    {
      "updated": "2026-06-14T17:00:58Z",
      "n_experiments": 60,
      "n_candidates": 0,
      "funnel": {
        "raw_significant": 43,
        "after_fdr": 42,
        "after_holdout": 0
      }
    },
    {
      "updated": "2026-06-14T19:06:17Z",
      "n_experiments": 60,
      "n_candidates": 0,
      "funnel": {
        "raw_significant": 43,
        "after_fdr": 42,
        "after_holdout": 0
      }
    },
    {
      "updated": "2026-06-14T20:53:02Z",
      "n_experiments": 60,
      "n_candidates": 0,
      "funnel": {
        "raw_significant": 43,
        "after_fdr": 42,
        "after_holdout": 0
      }
    },
    {
      "updated": "2026-06-14T22:48:19Z",
      "n_experiments": 60,
      "n_candidates": 0,
      "funnel": {
        "raw_significant": 43,
        "after_fdr": 42,
        "after_holdout": 0
      }
    },
    {
      "updated": "2026-06-15T01:52:21Z",
      "n_experiments": 60,
      "n_candidates": 0,
      "funnel": {
        "raw_significant": 43,
        "after_fdr": 42,
        "after_holdout": 0
      }
    },
    {
      "updated": "2026-06-15T07:52:05Z",
      "n_experiments": 60,
      "n_candidates": 0,
      "funnel": {
        "raw_significant": 43,
        "after_fdr": 42,
        "after_holdout": 0
      }
    },
    {
      "updated": "2026-06-15T13:35:59Z",
      "n_experiments": 60,
      "n_candidates": 0,
      "funnel": {
        "raw_significant": 44,
        "after_fdr": 44,
        "after_holdout": 0
      }
    },
    {
      "updated": "2026-06-15T14:49:38Z",
      "n_experiments": 60,
      "n_candidates": 0,
      "funnel": {
        "raw_significant": 44,
        "after_fdr": 44,
        "after_holdout": 0
      }
    },
    {
      "updated": "2026-06-15T19:20:51Z",
      "n_experiments": 60,
      "n_candidates": 0,
      "funnel": {
        "raw_significant": 44,
        "after_fdr": 44,
        "after_holdout": 0
      }
    },
    {
      "updated": "2026-06-15T22:25:29Z",
      "n_experiments": 60,
      "n_candidates": 0,
      "funnel": {
        "raw_significant": 44,
        "after_fdr": 44,
        "after_holdout": 0
      }
    },
    {
      "updated": "2026-06-15T23:22:20Z",
      "n_experiments": 60,
      "n_candidates": 0,
      "funnel": {
        "raw_significant": 44,
        "after_fdr": 44,
        "after_holdout": 0
      }
    },
    {
      "updated": "2026-06-16T00:16:23Z",
      "n_experiments": 60,
      "n_candidates": 0,
      "funnel": {
        "raw_significant": 44,
        "after_fdr": 44,
        "after_holdout": 0
      }
    },
    {
      "updated": "2026-06-16T05:50:27Z",
      "n_experiments": 60,
      "n_candidates": 0,
      "funnel": {
        "raw_significant": 44,
        "after_fdr": 44,
        "after_holdout": 0
      }
    },
    {
      "updated": "2026-06-16T11:48:38Z",
      "n_experiments": 60,
      "n_candidates": 0,
      "funnel": {
        "raw_significant": 44,
        "after_fdr": 44,
        "after_holdout": 0
      }
    },
    {
      "updated": "2026-06-16T12:32:04Z",
      "n_experiments": 60,
      "n_candidates": 0,
      "funnel": {
        "raw_significant": 44,
        "after_fdr": 44,
        "after_holdout": 0
      }
    },
    {
      "updated": "2026-06-16T17:36:02Z",
      "n_experiments": 60,
      "n_candidates": 24,
      "funnel": {
        "raw_significant": 44,
        "after_fdr": 44,
        "after_holdout": 24
      }
    },
    {
      "updated": "2026-06-16T21:32:52Z",
      "n_experiments": 60,
      "n_candidates": 24,
      "funnel": {
        "raw_significant": 44,
        "after_fdr": 44,
        "after_holdout": 24
      }
    },
    {
      "updated": "2026-06-16T23:10:29Z",
      "n_experiments": 60,
      "n_candidates": 24,
      "funnel": {
        "raw_significant": 44,
        "after_fdr": 44,
        "after_holdout": 24
      }
    },
    {
      "updated": "2026-06-17T01:56:16Z",
      "n_experiments": 60,
      "n_candidates": 24,
      "funnel": {
        "raw_significant": 44,
        "after_fdr": 44,
        "after_holdout": 24
      }
    },
    {
      "updated": "2026-06-17T07:41:55Z",
      "n_experiments": 60,
      "n_candidates": 24,
      "funnel": {
        "raw_significant": 44,
        "after_fdr": 44,
        "after_holdout": 24
      }
    },
    {
      "updated": "2026-06-17T12:05:28Z",
      "n_experiments": 60,
      "n_candidates": 24,
      "funnel": {
        "raw_significant": 44,
        "after_fdr": 44,
        "after_holdout": 24
      }
    },
    {
      "updated": "2026-06-17T12:42:28Z",
      "n_experiments": 60,
      "n_candidates": 24,
      "funnel": {
        "raw_significant": 44,
        "after_fdr": 44,
        "after_holdout": 24
      }
    },
    {
      "updated": "2026-06-17T16:55:50Z",
      "n_experiments": 60,
      "n_candidates": 11,
      "funnel": {
        "raw_significant": 44,
        "after_fdr": 44,
        "after_holdout": 11
      }
    },
    {
      "updated": "2026-06-17T19:43:41Z",
      "n_experiments": 60,
      "n_candidates": 11,
      "funnel": {
        "raw_significant": 44,
        "after_fdr": 44,
        "after_holdout": 11
      }
    },
    {
      "updated": "2026-06-17T22:25:54Z",
      "n_experiments": 60,
      "n_candidates": 11,
      "funnel": {
        "raw_significant": 44,
        "after_fdr": 44,
        "after_holdout": 11
      }
    },
    {
      "updated": "2026-06-17T23:04:22Z",
      "n_experiments": 60,
      "n_candidates": 11,
      "funnel": {
        "raw_significant": 44,
        "after_fdr": 44,
        "after_holdout": 11
      }
    },
    {
      "updated": "2026-06-18T00:03:50Z",
      "n_experiments": 60,
      "n_candidates": 11,
      "funnel": {
        "raw_significant": 44,
        "after_fdr": 44,
        "after_holdout": 11
      }
    },
    {
      "updated": "2026-06-18T05:20:09Z",
      "n_experiments": 60,
      "n_candidates": 11,
      "funnel": {
        "raw_significant": 44,
        "after_fdr": 44,
        "after_holdout": 11
      }
    },
    {
      "updated": "2026-06-18T09:59:57Z",
      "n_experiments": 60,
      "n_candidates": 11,
      "funnel": {
        "raw_significant": 44,
        "after_fdr": 44,
        "after_holdout": 11
      }
    },
    {
      "updated": "2026-06-18T11:41:19Z",
      "n_experiments": 60,
      "n_candidates": 11,
      "funnel": {
        "raw_significant": 44,
        "after_fdr": 44,
        "after_holdout": 11
      }
    },
    {
      "updated": "2026-06-18T13:55:27Z",
      "n_experiments": 60,
      "n_candidates": 19,
      "funnel": {
        "raw_significant": 45,
        "after_fdr": 44,
        "after_holdout": 19
      }
    },
    {
      "updated": "2026-06-18T17:46:10Z",
      "n_experiments": 60,
      "n_candidates": 19,
      "funnel": {
        "raw_significant": 45,
        "after_fdr": 44,
        "after_holdout": 19
      }
    },
    {
      "updated": "2026-06-18T20:51:53Z",
      "n_experiments": 60,
      "n_candidates": 19,
      "funnel": {
        "raw_significant": 45,
        "after_fdr": 44,
        "after_holdout": 19
      }
    },
    {
      "updated": "2026-06-18T23:25:00Z",
      "n_experiments": 60,
      "n_candidates": 19,
      "funnel": {
        "raw_significant": 45,
        "after_fdr": 44,
        "after_holdout": 19
      }
    },
    {
      "updated": "2026-06-19T02:20:14Z",
      "n_experiments": 60,
      "n_candidates": 19,
      "funnel": {
        "raw_significant": 45,
        "after_fdr": 44,
        "after_holdout": 19
      }
    },
    {
      "updated": "2026-06-19T07:43:59Z",
      "n_experiments": 60,
      "n_candidates": 19,
      "funnel": {
        "raw_significant": 45,
        "after_fdr": 44,
        "after_holdout": 19
      }
    },
    {
      "updated": "2026-06-19T11:51:44Z",
      "n_experiments": 60,
      "n_candidates": 19,
      "funnel": {
        "raw_significant": 45,
        "after_fdr": 44,
        "after_holdout": 19
      }
    },
    {
      "updated": "2026-06-19T12:37:51Z",
      "n_experiments": 60,
      "n_candidates": 19,
      "funnel": {
        "raw_significant": 45,
        "after_fdr": 44,
        "after_holdout": 19
      }
    },
    {
      "updated": "2026-06-19T16:26:24Z",
      "n_experiments": 60,
      "n_candidates": 19,
      "funnel": {
        "raw_significant": 45,
        "after_fdr": 44,
        "after_holdout": 19
      }
    },
    {
      "updated": "2026-06-19T18:21:55Z",
      "n_experiments": 60,
      "n_candidates": 19,
      "funnel": {
        "raw_significant": 45,
        "after_fdr": 44,
        "after_holdout": 19
      }
    },
    {
      "updated": "2026-06-19T20:19:46Z",
      "n_experiments": 60,
      "n_candidates": 19,
      "funnel": {
        "raw_significant": 45,
        "after_fdr": 44,
        "after_holdout": 19
      }
    },
    {
      "updated": "2026-06-19T21:49:04Z",
      "n_experiments": 60,
      "n_candidates": 19,
      "funnel": {
        "raw_significant": 45,
        "after_fdr": 44,
        "after_holdout": 19
      }
    },
    {
      "updated": "2026-06-19T22:39:08Z",
      "n_experiments": 60,
      "n_candidates": 19,
      "funnel": {
        "raw_significant": 45,
        "after_fdr": 44,
        "after_holdout": 19
      }
    },
    {
      "updated": "2026-06-19T23:43:27Z",
      "n_experiments": 60,
      "n_candidates": 19,
      "funnel": {
        "raw_significant": 45,
        "after_fdr": 44,
        "after_holdout": 19
      }
    },
    {
      "updated": "2026-06-20T04:56:09Z",
      "n_experiments": 60,
      "n_candidates": 19,
      "funnel": {
        "raw_significant": 45,
        "after_fdr": 44,
        "after_holdout": 19
      }
    },
    {
      "updated": "2026-06-20T08:40:39Z",
      "n_experiments": 60,
      "n_candidates": 19,
      "funnel": {
        "raw_significant": 45,
        "after_fdr": 44,
        "after_holdout": 19
      }
    },
    {
      "updated": "2026-06-20T10:23:01Z",
      "n_experiments": 60,
      "n_candidates": 19,
      "funnel": {
        "raw_significant": 45,
        "after_fdr": 44,
        "after_holdout": 19
      }
    },
    {
      "updated": "2026-06-20T11:38:27Z",
      "n_experiments": 60,
      "n_candidates": 19,
      "funnel": {
        "raw_significant": 45,
        "after_fdr": 44,
        "after_holdout": 19
      }
    },
    {
      "updated": "2026-06-20T14:46:02Z",
      "n_experiments": 60,
      "n_candidates": 19,
      "funnel": {
        "raw_significant": 45,
        "after_fdr": 44,
        "after_holdout": 19
      }
    },
    {
      "updated": "2026-06-20T17:06:03Z",
      "n_experiments": 60,
      "n_candidates": 19,
      "funnel": {
        "raw_significant": 45,
        "after_fdr": 44,
        "after_holdout": 19
      }
    },
    {
      "updated": "2026-06-20T19:01:37Z",
      "n_experiments": 60,
      "n_candidates": 19,
      "funnel": {
        "raw_significant": 45,
        "after_fdr": 44,
        "after_holdout": 19
      }
    },
    {
      "updated": "2026-06-20T20:55:08Z",
      "n_experiments": 60,
      "n_candidates": 19,
      "funnel": {
        "raw_significant": 45,
        "after_fdr": 44,
        "after_holdout": 19
      }
    },
    {
      "updated": "2026-06-20T22:48:44Z",
      "n_experiments": 60,
      "n_candidates": 19,
      "funnel": {
        "raw_significant": 45,
        "after_fdr": 44,
        "after_holdout": 19
      }
    },
    {
      "updated": "2026-06-21T01:53:51Z",
      "n_experiments": 60,
      "n_candidates": 19,
      "funnel": {
        "raw_significant": 45,
        "after_fdr": 44,
        "after_holdout": 19
      }
    },
    {
      "updated": "2026-06-21T07:24:02Z",
      "n_experiments": 60,
      "n_candidates": 19,
      "funnel": {
        "raw_significant": 45,
        "after_fdr": 44,
        "after_holdout": 19
      }
    },
    {
      "updated": "2026-06-21T11:01:06Z",
      "n_experiments": 60,
      "n_candidates": 19,
      "funnel": {
        "raw_significant": 45,
        "after_fdr": 44,
        "after_holdout": 19
      }
    },
    {
      "updated": "2026-06-21T13:30:04Z",
      "n_experiments": 60,
      "n_candidates": 19,
      "funnel": {
        "raw_significant": 45,
        "after_fdr": 44,
        "after_holdout": 19
      }
    },
    {
      "updated": "2026-06-21T15:29:43Z",
      "n_experiments": 60,
      "n_candidates": 19,
      "funnel": {
        "raw_significant": 45,
        "after_fdr": 44,
        "after_holdout": 19
      }
    },
    {
      "updated": "2026-06-21T17:07:52Z",
      "n_experiments": 60,
      "n_candidates": 19,
      "funnel": {
        "raw_significant": 45,
        "after_fdr": 44,
        "after_holdout": 19
      }
    },
    {
      "updated": "2026-06-21T19:06:55Z",
      "n_experiments": 60,
      "n_candidates": 19,
      "funnel": {
        "raw_significant": 45,
        "after_fdr": 44,
        "after_holdout": 19
      }
    },
    {
      "updated": "2026-06-21T20:59:52Z",
      "n_experiments": 60,
      "n_candidates": 19,
      "funnel": {
        "raw_significant": 45,
        "after_fdr": 44,
        "after_holdout": 19
      }
    },
    {
      "updated": "2026-06-21T22:48:34Z",
      "n_experiments": 60,
      "n_candidates": 19,
      "funnel": {
        "raw_significant": 45,
        "after_fdr": 44,
        "after_holdout": 19
      }
    },
    {
      "updated": "2026-06-22T01:54:39Z",
      "n_experiments": 60,
      "n_candidates": 19,
      "funnel": {
        "raw_significant": 45,
        "after_fdr": 44,
        "after_holdout": 19
      }
    },
    {
      "updated": "2026-06-22T07:55:12Z",
      "n_experiments": 60,
      "n_candidates": 19,
      "funnel": {
        "raw_significant": 45,
        "after_fdr": 44,
        "after_holdout": 19
      }
    },
    {
      "updated": "2026-06-22T13:15:20Z",
      "n_experiments": 60,
      "n_candidates": 19,
      "funnel": {
        "raw_significant": 45,
        "after_fdr": 44,
        "after_holdout": 19
      }
    },
    {
      "updated": "2026-06-22T13:57:06Z",
      "n_experiments": 60,
      "n_candidates": 24,
      "funnel": {
        "raw_significant": 51,
        "after_fdr": 48,
        "after_holdout": 24
      }
    },
    {
      "updated": "2026-06-22T18:40:37Z",
      "n_experiments": 60,
      "n_candidates": 24,
      "funnel": {
        "raw_significant": 51,
        "after_fdr": 48,
        "after_holdout": 24
      }
    },
    {
      "updated": "2026-06-22T21:47:44Z",
      "n_experiments": 60,
      "n_candidates": 24,
      "funnel": {
        "raw_significant": 51,
        "after_fdr": 48,
        "after_holdout": 24
      }
    },
    {
      "updated": "2026-06-22T23:09:07Z",
      "n_experiments": 60,
      "n_candidates": 24,
      "funnel": {
        "raw_significant": 51,
        "after_fdr": 48,
        "after_holdout": 24
      }
    },
    {
      "updated": "2026-06-22T23:57:22Z",
      "n_experiments": 60,
      "n_candidates": 24,
      "funnel": {
        "raw_significant": 51,
        "after_fdr": 48,
        "after_holdout": 24
      }
    },
    {
      "updated": "2026-06-23T04:45:39Z",
      "n_experiments": 60,
      "n_candidates": 24,
      "funnel": {
        "raw_significant": 51,
        "after_fdr": 48,
        "after_holdout": 24
      }
    },
    {
      "updated": "2026-06-23T08:50:57Z",
      "n_experiments": 60,
      "n_candidates": 24,
      "funnel": {
        "raw_significant": 51,
        "after_fdr": 48,
        "after_holdout": 24
      }
    },
    {
      "updated": "2026-06-23T10:53:37Z",
      "n_experiments": 60,
      "n_candidates": 24,
      "funnel": {
        "raw_significant": 51,
        "after_fdr": 48,
        "after_holdout": 24
      }
    },
    {
      "updated": "2026-06-23T12:28:50Z",
      "n_experiments": 60,
      "n_candidates": 24,
      "funnel": {
        "raw_significant": 51,
        "after_fdr": 48,
        "after_holdout": 24
      }
    },
    {
      "updated": "2026-06-23T15:39:58Z",
      "n_experiments": 60,
      "n_candidates": 37,
      "funnel": {
        "raw_significant": 51,
        "after_fdr": 48,
        "after_holdout": 37
      }
    },
    {
      "updated": "2026-06-23T18:28:55Z",
      "n_experiments": 60,
      "n_candidates": 37,
      "funnel": {
        "raw_significant": 51,
        "after_fdr": 48,
        "after_holdout": 37
      }
    },
    {
      "updated": "2026-06-23T20:38:22Z",
      "n_experiments": 60,
      "n_candidates": 37,
      "funnel": {
        "raw_significant": 51,
        "after_fdr": 48,
        "after_holdout": 37
      }
    },
    {
      "updated": "2026-06-23T22:54:42Z",
      "n_experiments": 60,
      "n_candidates": 37,
      "funnel": {
        "raw_significant": 51,
        "after_fdr": 48,
        "after_holdout": 37
      }
    },
    {
      "updated": "2026-06-24T00:26:21Z",
      "n_experiments": 60,
      "n_candidates": 37,
      "funnel": {
        "raw_significant": 51,
        "after_fdr": 48,
        "after_holdout": 37
      }
    },
    {
      "updated": "2026-06-24T04:54:00Z",
      "n_experiments": 60,
      "n_candidates": 37,
      "funnel": {
        "raw_significant": 51,
        "after_fdr": 48,
        "after_holdout": 37
      }
    },
    {
      "updated": "2026-06-24T08:47:53Z",
      "n_experiments": 60,
      "n_candidates": 37,
      "funnel": {
        "raw_significant": 51,
        "after_fdr": 48,
        "after_holdout": 37
      }
    },
    {
      "updated": "2026-06-24T10:37:45Z",
      "n_experiments": 60,
      "n_candidates": 37,
      "funnel": {
        "raw_significant": 51,
        "after_fdr": 48,
        "after_holdout": 37
      }
    },
    {
      "updated": "2026-06-24T12:15:01Z",
      "n_experiments": 60,
      "n_candidates": 37,
      "funnel": {
        "raw_significant": 51,
        "after_fdr": 48,
        "after_holdout": 37
      }
    },
    {
      "updated": "2026-06-24T15:24:37Z",
      "n_experiments": 60,
      "n_candidates": 48,
      "funnel": {
        "raw_significant": 51,
        "after_fdr": 48,
        "after_holdout": 48
      }
    },
    {
      "updated": "2026-06-24T17:33:34Z",
      "n_experiments": 60,
      "n_candidates": 48,
      "funnel": {
        "raw_significant": 51,
        "after_fdr": 48,
        "after_holdout": 48
      }
    },
    {
      "updated": "2026-06-24T19:19:19Z",
      "n_experiments": 60,
      "n_candidates": 48,
      "funnel": {
        "raw_significant": 51,
        "after_fdr": 48,
        "after_holdout": 48
      }
    },
    {
      "updated": "2026-06-24T21:12:21Z",
      "n_experiments": 60,
      "n_candidates": 48,
      "funnel": {
        "raw_significant": 51,
        "after_fdr": 48,
        "after_holdout": 48
      }
    },
    {
      "updated": "2026-06-24T22:55:52Z",
      "n_experiments": 60,
      "n_candidates": 48,
      "funnel": {
        "raw_significant": 51,
        "after_fdr": 48,
        "after_holdout": 48
      }
    },
    {
      "updated": "2026-06-25T01:41:31Z",
      "n_experiments": 60,
      "n_candidates": 48,
      "funnel": {
        "raw_significant": 51,
        "after_fdr": 48,
        "after_holdout": 48
      }
    },
    {
      "updated": "2026-06-25T06:40:40Z",
      "n_experiments": 60,
      "n_candidates": 48,
      "funnel": {
        "raw_significant": 51,
        "after_fdr": 48,
        "after_holdout": 48
      }
    },
    {
      "updated": "2026-06-25T10:34:11Z",
      "n_experiments": 60,
      "n_candidates": 48,
      "funnel": {
        "raw_significant": 51,
        "after_fdr": 48,
        "after_holdout": 48
      }
    },
    {
      "updated": "2026-06-25T12:47:11Z",
      "n_experiments": 60,
      "n_candidates": 48,
      "funnel": {
        "raw_significant": 51,
        "after_fdr": 48,
        "after_holdout": 48
      }
    }
  ],
  "latest": {
    "updated": "2026-06-25T12:47:11Z",
    "n_experiments": 60,
    "n_valid": 60,
    "n_errors": 0,
    "explore_dates": [
      "2026-04-17",
      "2026-04-27",
      "2026-05-03",
      "2026-05-04",
      "2026-05-05",
      "2026-05-06",
      "2026-05-07",
      "2026-05-08",
      "2026-05-09",
      "2026-05-10",
      "2026-05-11",
      "2026-05-12",
      "2026-05-13",
      "2026-05-14",
      "2026-05-15",
      "2026-05-16",
      "2026-05-17",
      "2026-05-18",
      "2026-05-19",
      "2026-05-20",
      "2026-05-21",
      "2026-05-22",
      "2026-05-23",
      "2026-05-24",
      "2026-05-25",
      "2026-05-26",
      "2026-05-27",
      "2026-05-28",
      "2026-05-29",
      "2026-05-30",
      "2026-05-31",
      "2026-06-01",
      "2026-06-02",
      "2026-06-03",
      "2026-06-04",
      "2026-06-05",
      "2026-06-06",
      "2026-06-07"
    ],
    "holdout_dates": [
      "2026-06-08",
      "2026-06-09",
      "2026-06-10",
      "2026-06-11",
      "2026-06-12",
      "2026-06-13",
      "2026-06-14",
      "2026-06-15",
      "2026-06-16"
    ],
    "data_quality": {
      "n_rows": 3803,
      "missing_rates": {
        "ta_rsi14": 0.0,
        "ta_hv20": 0.0,
        "confidence": 0.0,
        "news_best_conf": 0.132,
        "news_z": 0.143,
        "sentiment_score": 0.107,
        "sentiment_total": 0.107,
        "fundamental_score": 0.198,
        "quality_score": 0.198,
        "growth_score": 0.198,
        "health_score": 0.198,
        "insider_score": 0.127
      },
      "outlier_counts": {
        "ta_hv20": 5,
        "sentiment_score": 64,
        "sentiment_total": 9
      },
      "look_ahead_suspects": [],
      "issues": [],
      "pass": true
    },
    "defense_funnel": {
      "raw_significant": 51,
      "after_fdr": 48,
      "after_holdout": 48
    },
    "candidates": [
      {
        "id": "Ridge_ta_only_all_5d",
        "config": {
          "id": "Ridge_ta_only_all_5d",
          "model": "Ridge",
          "features": "ta_only",
          "universe": "all",
          "horizon": 5
        },
        "explore_alpha": 1.1781,
        "explore_p": 2.6e-05,
        "holdout_alpha": 0.4801,
        "status": "CANDIDATE \u2014 awaiting out-of-time confirmation"
      },
      {
        "id": "Ridge_ta_only_high_vol_5d",
        "config": {
          "id": "Ridge_ta_only_high_vol_5d",
          "model": "Ridge",
          "features": "ta_only",
          "universe": "high_vol",
          "horizon": 5
        },
        "explore_alpha": 2.1566,
        "explore_p": 0.001173,
        "holdout_alpha": 0.5692,
        "status": "CANDIDATE \u2014 awaiting out-of-time confirmation"
      },
      {
        "id": "Lasso_ta_only_all_5d",
        "config": {
          "id": "Lasso_ta_only_all_5d",
          "model": "Lasso",
          "features": "ta_only",
          "universe": "all",
          "horizon": 5
        },
        "explore_alpha": 1.3394,
        "explore_p": 7.2e-05,
        "holdout_alpha": 0.514,
        "status": "CANDIDATE \u2014 awaiting out-of-time confirmation"
      },
      {
        "id": "Lasso_ta_only_high_vol_5d",
        "config": {
          "id": "Lasso_ta_only_high_vol_5d",
          "model": "Lasso",
          "features": "ta_only",
          "universe": "high_vol",
          "horizon": 5
        },
        "explore_alpha": 2.0793,
        "explore_p": 0.001784,
        "holdout_alpha": 0.9198,
        "status": "CANDIDATE \u2014 awaiting out-of-time confirmation"
      },
      {
        "id": "RandomForest_ta_only_all_5d",
        "config": {
          "id": "RandomForest_ta_only_all_5d",
          "model": "RandomForest",
          "features": "ta_only",
          "universe": "all",
          "horizon": 5
        },
        "explore_alpha": 1.6505,
        "explore_p": 1e-06,
        "holdout_alpha": 1.5515,
        "status": "CANDIDATE \u2014 awaiting out-of-time confirmation"
      },
      {
        "id": "RandomForest_ta_only_high_vol_5d",
        "config": {
          "id": "RandomForest_ta_only_high_vol_5d",
          "model": "RandomForest",
          "features": "ta_only",
          "universe": "high_vol",
          "horizon": 5
        },
        "explore_alpha": 2.9049,
        "explore_p": 7.5e-05,
        "holdout_alpha": 1.3386,
        "status": "CANDIDATE \u2014 awaiting out-of-time confirmation"
      },
      {
        "id": "RandomForest_ta_only_low_vol_5d",
        "config": {
          "id": "RandomForest_ta_only_low_vol_5d",
          "model": "RandomForest",
          "features": "ta_only",
          "universe": "low_vol",
          "horizon": 5
        },
        "explore_alpha": 0.7012,
        "explore_p": 0.029781,
        "holdout_alpha": 1.5025,
        "status": "CANDIDATE \u2014 awaiting out-of-time confirmation"
      },
      {
        "id": "GradientBoosting_ta_only_all_5d",
        "config": {
          "id": "GradientBoosting_ta_only_all_5d",
          "model": "GradientBoosting",
          "features": "ta_only",
          "universe": "all",
          "horizon": 5
        },
        "explore_alpha": 1.6519,
        "explore_p": 0.0,
        "holdout_alpha": 1.8832,
        "status": "CANDIDATE \u2014 awaiting out-of-time confirmation"
      },
      {
        "id": "GradientBoosting_ta_only_high_vol_5d",
        "config": {
          "id": "GradientBoosting_ta_only_high_vol_5d",
          "model": "GradientBoosting",
          "features": "ta_only",
          "universe": "high_vol",
          "horizon": 5
        },
        "explore_alpha": 2.7777,
        "explore_p": 4.1e-05,
        "holdout_alpha": 1.602,
        "status": "CANDIDATE \u2014 awaiting out-of-time confirmation"
      },
      {
        "id": "Ridge_ta_news_all_5d",
        "config": {
          "id": "Ridge_ta_news_all_5d",
          "model": "Ridge",
          "features": "ta_news",
          "universe": "all",
          "horizon": 5
        },
        "explore_alpha": 1.1056,
        "explore_p": 0.001971,
        "holdout_alpha": 0.4802,
        "status": "CANDIDATE \u2014 awaiting out-of-time confirmation"
      },
      {
        "id": "Ridge_ta_news_high_vol_5d",
        "config": {
          "id": "Ridge_ta_news_high_vol_5d",
          "model": "Ridge",
          "features": "ta_news",
          "universe": "high_vol",
          "horizon": 5
        },
        "explore_alpha": 1.7221,
        "explore_p": 0.010985,
        "holdout_alpha": 0.353,
        "status": "CANDIDATE \u2014 awaiting out-of-time confirmation"
      },
      {
        "id": "Lasso_ta_news_all_5d",
        "config": {
          "id": "Lasso_ta_news_all_5d",
          "model": "Lasso",
          "features": "ta_news",
          "universe": "all",
          "horizon": 5
        },
        "explore_alpha": 1.258,
        "explore_p": 7.9e-05,
        "holdout_alpha": 0.5805,
        "status": "CANDIDATE \u2014 awaiting out-of-time confirmation"
      },
      {
        "id": "Lasso_ta_news_high_vol_5d",
        "config": {
          "id": "Lasso_ta_news_high_vol_5d",
          "model": "Lasso",
          "features": "ta_news",
          "universe": "high_vol",
          "horizon": 5
        },
        "explore_alpha": 1.9183,
        "explore_p": 0.004493,
        "holdout_alpha": 0.4915,
        "status": "CANDIDATE \u2014 awaiting out-of-time confirmation"
      },
      {
        "id": "RandomForest_ta_news_all_5d",
        "config": {
          "id": "RandomForest_ta_news_all_5d",
          "model": "RandomForest",
          "features": "ta_news",
          "universe": "all",
          "horizon": 5
        },
        "explore_alpha": 1.7615,
        "explore_p": 0.0,
        "holdout_alpha": 1.7295,
        "status": "CANDIDATE \u2014 awaiting out-of-time confirmation"
      },
      {
        "id": "RandomForest_ta_news_high_vol_5d",
        "config": {
          "id": "RandomForest_ta_news_high_vol_5d",
          "model": "RandomForest",
          "features": "ta_news",
          "universe": "high_vol",
          "horizon": 5
        },
        "explore_alpha": 2.9353,
        "explore_p": 7.6e-05,
        "holdout_alpha": 2.1603,
        "status": "CANDIDATE \u2014 awaiting out-of-time confirmation"
      },
      {
        "id": "RandomForest_ta_news_low_vol_5d",
        "config": {
          "id": "RandomForest_ta_news_low_vol_5d",
          "model": "RandomForest",
          "features": "ta_news",
          "universe": "low_vol",
          "horizon": 5
        },
        "explore_alpha": 0.839,
        "explore_p": 0.012738,
        "holdout_alpha": 1.3853,
        "status": "CANDIDATE \u2014 awaiting out-of-time confirmation"
      },
      {
        "id": "GradientBoosting_ta_news_all_5d",
        "config": {
          "id": "GradientBoosting_ta_news_all_5d",
          "model": "GradientBoosting",
          "features": "ta_news",
          "universe": "all",
          "horizon": 5
        },
        "explore_alpha": 1.7327,
        "explore_p": 0.0,
        "holdout_alpha": 1.7486,
        "status": "CANDIDATE \u2014 awaiting out-of-time confirmation"
      },
      {
        "id": "GradientBoosting_ta_news_high_vol_5d",
        "config": {
          "id": "GradientBoosting_ta_news_high_vol_5d",
          "model": "GradientBoosting",
          "features": "ta_news",
          "universe": "high_vol",
          "horizon": 5
        },
        "explore_alpha": 2.8787,
        "explore_p": 3.4e-05,
        "holdout_alpha": 1.5344,
        "status": "CANDIDATE \u2014 awaiting out-of-time confirmation"
      },
      {
        "id": "Ridge_ta_fundamental_all_5d",
        "config": {
          "id": "Ridge_ta_fundamental_all_5d",
          "model": "Ridge",
          "features": "ta_fundamental",
          "universe": "all",
          "horizon": 5
        },
        "explore_alpha": 1.2123,
        "explore_p": 2.3e-05,
        "holdout_alpha": 0.6399,
        "status": "CANDIDATE \u2014 awaiting out-of-time confirmation"
      },
      {
        "id": "Ridge_ta_fundamental_high_vol_5d",
        "config": {
          "id": "Ridge_ta_fundamental_high_vol_5d",
          "model": "Ridge",
          "features": "ta_fundamental",
          "universe": "high_vol",
          "horizon": 5
        },
        "explore_alpha": 2.1342,
        "explore_p": 0.001297,
        "holdout_alpha": 0.4314,
        "status": "CANDIDATE \u2014 awaiting out-of-time confirmation"
      },
      {
        "id": "Lasso_ta_fundamental_all_5d",
        "config": {
          "id": "Lasso_ta_fundamental_all_5d",
          "model": "Lasso",
          "features": "ta_fundamental",
          "universe": "all",
          "horizon": 5
        },
        "explore_alpha": 1.2845,
        "explore_p": 0.0001,
        "holdout_alpha": 0.5969,
        "status": "CANDIDATE \u2014 awaiting out-of-time confirmation"
      },
      {
        "id": "Lasso_ta_fundamental_high_vol_5d",
        "config": {
          "id": "Lasso_ta_fundamental_high_vol_5d",
          "model": "Lasso",
          "features": "ta_fundamental",
          "universe": "high_vol",
          "horizon": 5
        },
        "explore_alpha": 2.0929,
        "explore_p": 0.001684,
        "holdout_alpha": 0.9898,
        "status": "CANDIDATE \u2014 awaiting out-of-time confirmation"
      },
      {
        "id": "RandomForest_ta_fundamental_all_5d",
        "config": {
          "id": "RandomForest_ta_fundamental_all_5d",
          "model": "RandomForest",
          "features": "ta_fundamental",
          "universe": "all",
          "horizon": 5
        },
        "explore_alpha": 2.0824,
        "explore_p": 0.0,
        "holdout_alpha": 2.2653,
        "status": "CANDIDATE \u2014 awaiting out-of-time confirmation"
      },
      {
        "id": "RandomForest_ta_fundamental_high_vol_5d",
        "config": {
          "id": "RandomForest_ta_fundamental_high_vol_5d",
          "model": "RandomForest",
          "features": "ta_fundamental",
          "universe": "high_vol",
          "horizon": 5
        },
        "explore_alpha": 3.3108,
        "explore_p": 3e-06,
        "holdout_alpha": 2.6465,
        "status": "CANDIDATE \u2014 awaiting out-of-time confirmation"
      },
      {
        "id": "RandomForest_ta_fundamental_low_vol_5d",
        "config": {
          "id": "RandomForest_ta_fundamental_low_vol_5d",
          "model": "RandomForest",
          "features": "ta_fundamental",
          "universe": "low_vol",
          "horizon": 5
        },
        "explore_alpha": 1.2475,
        "explore_p": 0.000224,
        "holdout_alpha": 1.9983,
        "status": "CANDIDATE \u2014 awaiting out-of-time confirmation"
      },
      {
        "id": "GradientBoosting_ta_fundamental_all_5d",
        "config": {
          "id": "GradientBoosting_ta_fundamental_all_5d",
          "model": "GradientBoosting",
          "features": "ta_fundamental",
          "universe": "all",
          "horizon": 5
        },
        "explore_alpha": 2.1649,
        "explore_p": 0.0,
        "holdout_alpha": 2.7763,
        "status": "CANDIDATE \u2014 awaiting out-of-time confirmation"
      },
      {
        "id": "GradientBoosting_ta_fundamental_high_vol_5d",
        "config": {
          "id": "GradientBoosting_ta_fundamental_high_vol_5d",
          "model": "GradientBoosting",
          "features": "ta_fundamental",
          "universe": "high_vol",
          "horizon": 5
        },
        "explore_alpha": 3.8719,
        "explore_p": 0.0,
        "holdout_alpha": 3.2724,
        "status": "CANDIDATE \u2014 awaiting out-of-time confirmation"
      },
      {
        "id": "GradientBoosting_ta_fundamental_low_vol_5d",
        "config": {
          "id": "GradientBoosting_ta_fundamental_low_vol_5d",
          "model": "GradientBoosting",
          "features": "ta_fundamental",
          "universe": "low_vol",
          "horizon": 5
        },
        "explore_alpha": 1.2425,
        "explore_p": 0.000409,
        "holdout_alpha": 2.1192,
        "status": "CANDIDATE \u2014 awaiting out-of-time confirmation"
      },
      {
        "id": "Ridge_ta_sentiment_all_5d",
        "config": {
          "id": "Ridge_ta_sentiment_all_5d",
          "model": "Ridge",
          "features": "ta_sentiment",
          "universe": "all",
          "horizon": 5
        },
        "explore_alpha": 1.1699,
        "explore_p": 4.5e-05,
        "holdout_alpha": 0.4781,
        "status": "CANDIDATE \u2014 awaiting out-of-time confirmation"
      },
      {
        "id": "Ridge_ta_sentiment_high_vol_5d",
        "config": {
          "id": "Ridge_ta_sentiment_high_vol_5d",
          "model": "Ridge",
          "features": "ta_sentiment",
          "universe": "high_vol",
          "horizon": 5
        },
        "explore_alpha": 2.1533,
        "explore_p": 0.001156,
        "holdout_alpha": 0.5351,
        "status": "CANDIDATE \u2014 awaiting out-of-time confirmation"
      },
      {
        "id": "Lasso_ta_sentiment_all_5d",
        "config": {
          "id": "Lasso_ta_sentiment_all_5d",
          "model": "Lasso",
          "features": "ta_sentiment",
          "universe": "all",
          "horizon": 5
        },
        "explore_alpha": 1.3509,
        "explore_p": 6.2e-05,
        "holdout_alpha": 0.5513,
        "status": "CANDIDATE \u2014 awaiting out-of-time confirmation"
      },
      {
        "id": "Lasso_ta_sentiment_high_vol_5d",
        "config": {
          "id": "Lasso_ta_sentiment_high_vol_5d",
          "model": "Lasso",
          "features": "ta_sentiment",
          "universe": "high_vol",
          "horizon": 5
        },
        "explore_alpha": 2.0793,
        "explore_p": 0.001784,
        "holdout_alpha": 0.9198,
        "status": "CANDIDATE \u2014 awaiting out-of-time confirmation"
      },
      {
        "id": "RandomForest_ta_sentiment_all_5d",
        "config": {
          "id": "RandomForest_ta_sentiment_all_5d",
          "model": "RandomForest",
          "features": "ta_sentiment",
          "universe": "all",
          "horizon": 5
        },
        "explore_alpha": 1.6543,
        "explore_p": 1e-06,
        "holdout_alpha": 1.5745,
        "status": "CANDIDATE \u2014 awaiting out-of-time confirmation"
      },
      {
        "id": "RandomForest_ta_sentiment_high_vol_5d",
        "config": {
          "id": "RandomForest_ta_sentiment_high_vol_5d",
          "model": "RandomForest",
          "features": "ta_sentiment",
          "universe": "high_vol",
          "horizon": 5
        },
        "explore_alpha": 2.8967,
        "explore_p": 8.3e-05,
        "holdout_alpha": 1.3386,
        "status": "CANDIDATE \u2014 awaiting out-of-time confirmation"
      },
      {
        "id": "RandomForest_ta_sentiment_low_vol_5d",
        "config": {
          "id": "RandomForest_ta_sentiment_low_vol_5d",
          "model": "RandomForest",
          "features": "ta_sentiment",
          "universe": "low_vol",
          "horizon": 5
        },
        "explore_alpha": 0.7312,
        "explore_p": 0.022896,
        "holdout_alpha": 1.5328,
        "status": "CANDIDATE \u2014 awaiting out-of-time confirmation"
      },
      {
        "id": "GradientBoosting_ta_sentiment_all_5d",
        "config": {
          "id": "GradientBoosting_ta_sentiment_all_5d",
          "model": "GradientBoosting",
          "features": "ta_sentiment",
          "universe": "all",
          "horizon": 5
        },
        "explore_alpha": 1.5886,
        "explore_p": 0.0,
        "holdout_alpha": 1.753,
        "status": "CANDIDATE \u2014 awaiting out-of-time confirmation"
      },
      {
        "id": "GradientBoosting_ta_sentiment_high_vol_5d",
        "config": {
          "id": "GradientBoosting_ta_sentiment_high_vol_5d",
          "model": "GradientBoosting",
          "features": "ta_sentiment",
          "universe": "high_vol",
          "horizon": 5
        },
        "explore_alpha": 2.8304,
        "explore_p": 3.2e-05,
        "holdout_alpha": 1.611,
        "status": "CANDIDATE \u2014 awaiting out-of-time confirmation"
      },
      {
        "id": "Ridge_all_features_all_5d",
        "config": {
          "id": "Ridge_all_features_all_5d",
          "model": "Ridge",
          "features": "all_features",
          "universe": "all",
          "horizon": 5
        },
        "explore_alpha": 1.0362,
        "explore_p": 0.002153,
        "holdout_alpha": 0.5813,
        "status": "CANDIDATE \u2014 awaiting out-of-time confirmation"
      },
      {
        "id": "Ridge_all_features_high_vol_5d",
        "config": {
          "id": "Ridge_all_features_high_vol_5d",
          "model": "Ridge",
          "features": "all_features",
          "universe": "high_vol",
          "horizon": 5
        },
        "explore_alpha": 1.554,
        "explore_p": 0.020566,
        "holdout_alpha": 0.5906,
        "status": "CANDIDATE \u2014 awaiting out-of-time confirmation"
      },
      {
        "id": "Ridge_all_features_low_vol_5d",
        "config": {
          "id": "Ridge_all_features_low_vol_5d",
          "model": "Ridge",
          "features": "all_features",
          "universe": "low_vol",
          "horizon": 5
        },
        "explore_alpha": 0.7088,
        "explore_p": 0.034821,
        "holdout_alpha": 1.3932,
        "status": "CANDIDATE \u2014 awaiting out-of-time confirmation"
      },
      {
        "id": "Lasso_all_features_all_5d",
        "config": {
          "id": "Lasso_all_features_all_5d",
          "model": "Lasso",
          "features": "all_features",
          "universe": "all",
          "horizon": 5
        },
        "explore_alpha": 1.2163,
        "explore_p": 0.0001,
        "holdout_alpha": 0.5111,
        "status": "CANDIDATE \u2014 awaiting out-of-time confirmation"
      },
      {
        "id": "Lasso_all_features_high_vol_5d",
        "config": {
          "id": "Lasso_all_features_high_vol_5d",
          "model": "Lasso",
          "features": "all_features",
          "universe": "high_vol",
          "horizon": 5
        },
        "explore_alpha": 1.7952,
        "explore_p": 0.007724,
        "holdout_alpha": 0.7469,
        "status": "CANDIDATE \u2014 awaiting out-of-time confirmation"
      },
      {
        "id": "RandomForest_all_features_all_5d",
        "config": {
          "id": "RandomForest_all_features_all_5d",
          "model": "RandomForest",
          "features": "all_features",
          "universe": "all",
          "horizon": 5
        },
        "explore_alpha": 2.1053,
        "explore_p": 0.0,
        "holdout_alpha": 2.1467,
        "status": "CANDIDATE \u2014 awaiting out-of-time confirmation"
      },
      {
        "id": "RandomForest_all_features_high_vol_5d",
        "config": {
          "id": "RandomForest_all_features_high_vol_5d",
          "model": "RandomForest",
          "features": "all_features",
          "universe": "high_vol",
          "horizon": 5
        },
        "explore_alpha": 3.3139,
        "explore_p": 6e-06,
        "holdout_alpha": 2.7007,
        "status": "CANDIDATE \u2014 awaiting out-of-time confirmation"
      },
      {
        "id": "RandomForest_all_features_low_vol_5d",
        "config": {
          "id": "RandomForest_all_features_low_vol_5d",
          "model": "RandomForest",
          "features": "all_features",
          "universe": "low_vol",
          "horizon": 5
        },
        "explore_alpha": 1.2783,
        "explore_p": 5.6e-05,
        "holdout_alpha": 2.0292,
        "status": "CANDIDATE \u2014 awaiting out-of-time confirmation"
      },
      {
        "id": "GradientBoosting_all_features_all_5d",
        "config": {
          "id": "GradientBoosting_all_features_all_5d",
          "model": "GradientBoosting",
          "features": "all_features",
          "universe": "all",
          "horizon": 5
        },
        "explore_alpha": 2.1701,
        "explore_p": 0.0,
        "holdout_alpha": 2.7077,
        "status": "CANDIDATE \u2014 awaiting out-of-time confirmation"
      },
      {
        "id": "GradientBoosting_all_features_high_vol_5d",
        "config": {
          "id": "GradientBoosting_all_features_high_vol_5d",
          "model": "GradientBoosting",
          "features": "all_features",
          "universe": "high_vol",
          "horizon": 5
        },
        "explore_alpha": 3.7968,
        "explore_p": 0.0,
        "holdout_alpha": 2.7783,
        "status": "CANDIDATE \u2014 awaiting out-of-time confirmation"
      },
      {
        "id": "GradientBoosting_all_features_low_vol_5d",
        "config": {
          "id": "GradientBoosting_all_features_low_vol_5d",
          "model": "GradientBoosting",
          "features": "all_features",
          "universe": "low_vol",
          "horizon": 5
        },
        "explore_alpha": 1.2394,
        "explore_p": 0.001045,
        "holdout_alpha": 2.0773,
        "status": "CANDIDATE \u2014 awaiting out-of-time confirmation"
      }
    ],
    "all_results": [
      {
        "id": "Ridge_ta_only_all_5d",
        "status": "CANDIDATE",
        "alpha": 1.1781,
        "p": 2.6e-05,
        "acc": 0.5299,
        "n_folds": 24
      },
      {
        "id": "Ridge_ta_only_high_vol_5d",
        "status": "CANDIDATE",
        "alpha": 2.1566,
        "p": 0.001173,
        "acc": 0.5386,
        "n_folds": 24
      },
      {
        "id": "Ridge_ta_only_low_vol_5d",
        "status": "rejected",
        "alpha": 0.3802,
        "p": 0.17896,
        "acc": 0.5525,
        "n_folds": 24
      },
      {
        "id": "Lasso_ta_only_all_5d",
        "status": "CANDIDATE",
        "alpha": 1.3394,
        "p": 7.2e-05,
        "acc": 0.5416,
        "n_folds": 24
      },
      {
        "id": "Lasso_ta_only_high_vol_5d",
        "status": "CANDIDATE",
        "alpha": 2.0793,
        "p": 0.001784,
        "acc": 0.5461,
        "n_folds": 24
      },
      {
        "id": "Lasso_ta_only_low_vol_5d",
        "status": "rejected",
        "alpha": 0.1601,
        "p": 0.575454,
        "acc": 0.548,
        "n_folds": 24
      },
      {
        "id": "RandomForest_ta_only_all_5d",
        "status": "CANDIDATE",
        "alpha": 1.6505,
        "p": 1e-06,
        "acc": 0.5825,
        "n_folds": 24
      },
      {
        "id": "RandomForest_ta_only_high_vol_5d",
        "status": "CANDIDATE",
        "alpha": 2.9049,
        "p": 7.5e-05,
        "acc": 0.5764,
        "n_folds": 24
      },
      {
        "id": "RandomForest_ta_only_low_vol_5d",
        "status": "CANDIDATE",
        "alpha": 0.7012,
        "p": 0.029781,
        "acc": 0.6067,
        "n_folds": 24
      },
      {
        "id": "GradientBoosting_ta_only_all_5d",
        "status": "CANDIDATE",
        "alpha": 1.6519,
        "p": 0.0,
        "acc": 0.5715,
        "n_folds": 24
      },
      {
        "id": "GradientBoosting_ta_only_high_vol_5d",
        "status": "CANDIDATE",
        "alpha": 2.7777,
        "p": 4.1e-05,
        "acc": 0.5795,
        "n_folds": 24
      },
      {
        "id": "GradientBoosting_ta_only_low_vol_5d",
        "status": "rejected",
        "alpha": 0.6159,
        "p": 0.08408,
        "acc": 0.5962,
        "n_folds": 24
      },
      {
        "id": "Ridge_ta_news_all_5d",
        "status": "CANDIDATE",
        "alpha": 1.1056,
        "p": 0.001971,
        "acc": 0.5235,
        "n_folds": 24
      },
      {
        "id": "Ridge_ta_news_high_vol_5d",
        "status": "CANDIDATE",
        "alpha": 1.7221,
        "p": 0.010985,
        "acc": 0.5254,
        "n_folds": 24
      },
      {
        "id": "Ridge_ta_news_low_vol_5d",
        "status": "rejected",
        "alpha": 0.384,
        "p": 0.200177,
        "acc": 0.5491,
        "n_folds": 24
      },
      {
        "id": "Lasso_ta_news_all_5d",
        "status": "CANDIDATE",
        "alpha": 1.258,
        "p": 7.9e-05,
        "acc": 0.535,
        "n_folds": 24
      },
      {
        "id": "Lasso_ta_news_high_vol_5d",
        "status": "CANDIDATE",
        "alpha": 1.9183,
        "p": 0.004493,
        "acc": 0.5313,
        "n_folds": 24
      },
      {
        "id": "Lasso_ta_news_low_vol_5d",
        "status": "rejected",
        "alpha": 0.1852,
        "p": 0.537621,
        "acc": 0.5563,
        "n_folds": 24
      },
      {
        "id": "RandomForest_ta_news_all_5d",
        "status": "CANDIDATE",
        "alpha": 1.7615,
        "p": 0.0,
        "acc": 0.589,
        "n_folds": 24
      },
      {
        "id": "RandomForest_ta_news_high_vol_5d",
        "status": "CANDIDATE",
        "alpha": 2.9353,
        "p": 7.6e-05,
        "acc": 0.5764,
        "n_folds": 24
      },
      {
        "id": "RandomForest_ta_news_low_vol_5d",
        "status": "CANDIDATE",
        "alpha": 0.839,
        "p": 0.012738,
        "acc": 0.6173,
        "n_folds": 24
      },
      {
        "id": "GradientBoosting_ta_news_all_5d",
        "status": "CANDIDATE",
        "alpha": 1.7327,
        "p": 0.0,
        "acc": 0.5733,
        "n_folds": 24
      },
      {
        "id": "GradientBoosting_ta_news_high_vol_5d",
        "status": "CANDIDATE",
        "alpha": 2.8787,
        "p": 3.4e-05,
        "acc": 0.5815,
        "n_folds": 24
      },
      {
        "id": "GradientBoosting_ta_news_low_vol_5d",
        "status": "rejected",
        "alpha": 0.5561,
        "p": 0.168734,
        "acc": 0.585,
        "n_folds": 24
      },
      {
        "id": "Ridge_ta_fundamental_all_5d",
        "status": "CANDIDATE",
        "alpha": 1.2123,
        "p": 2.3e-05,
        "acc": 0.5304,
        "n_folds": 24
      },
      {
        "id": "Ridge_ta_fundamental_high_vol_5d",
        "status": "CANDIDATE",
        "alpha": 2.1342,
        "p": 0.001297,
        "acc": 0.5444,
        "n_folds": 24
      },
      {
        "id": "Ridge_ta_fundamental_low_vol_5d",
        "status": "raw_sig_fdr_fail",
        "alpha": 0.606,
        "p": 0.049335,
        "acc": 0.5704,
        "n_folds": 24
      },
      {
        "id": "Lasso_ta_fundamental_all_5d",
        "status": "CANDIDATE",
        "alpha": 1.2845,
        "p": 0.0001,
        "acc": 0.5347,
        "n_folds": 24
      },
      {
        "id": "Lasso_ta_fundamental_high_vol_5d",
        "status": "CANDIDATE",
        "alpha": 2.0929,
        "p": 0.001684,
        "acc": 0.5461,
        "n_folds": 24
      },
      {
        "id": "Lasso_ta_fundamental_low_vol_5d",
        "status": "rejected",
        "alpha": 0.552,
        "p": 0.072282,
        "acc": 0.5636,
        "n_folds": 24
      },
      {
        "id": "RandomForest_ta_fundamental_all_5d",
        "status": "CANDIDATE",
        "alpha": 2.0824,
        "p": 0.0,
        "acc": 0.6084,
        "n_folds": 24
      },
      {
        "id": "RandomForest_ta_fundamental_high_vol_5d",
        "status": "CANDIDATE",
        "alpha": 3.3108,
        "p": 3e-06,
        "acc": 0.5928,
        "n_folds": 24
      },
      {
        "id": "RandomForest_ta_fundamental_low_vol_5d",
        "status": "CANDIDATE",
        "alpha": 1.2475,
        "p": 0.000224,
        "acc": 0.6662,
        "n_folds": 24
      },
      {
        "id": "GradientBoosting_ta_fundamental_all_5d",
        "status": "CANDIDATE",
        "alpha": 2.1649,
        "p": 0.0,
        "acc": 0.6011,
        "n_folds": 24
      },
      {
        "id": "GradientBoosting_ta_fundamental_high_vol_5d",
        "status": "CANDIDATE",
        "alpha": 3.8719,
        "p": 0.0,
        "acc": 0.6327,
        "n_folds": 24
      },
      {
        "id": "GradientBoosting_ta_fundamental_low_vol_5d",
        "status": "CANDIDATE",
        "alpha": 1.2425,
        "p": 0.000409,
        "acc": 0.6549,
        "n_folds": 24
      },
      {
        "id": "Ridge_ta_sentiment_all_5d",
        "status": "CANDIDATE",
        "alpha": 1.1699,
        "p": 4.5e-05,
        "acc": 0.5272,
        "n_folds": 24
      },
      {
        "id": "Ridge_ta_sentiment_high_vol_5d",
        "status": "CANDIDATE",
        "alpha": 2.1533,
        "p": 0.001156,
        "acc": 0.5393,
        "n_folds": 24
      },
      {
        "id": "Ridge_ta_sentiment_low_vol_5d",
        "status": "rejected",
        "alpha": 0.3745,
        "p": 0.19433,
        "acc": 0.5491,
        "n_folds": 24
      },
      {
        "id": "Lasso_ta_sentiment_all_5d",
        "status": "CANDIDATE",
        "alpha": 1.3509,
        "p": 6.2e-05,
        "acc": 0.5425,
        "n_folds": 24
      },
      {
        "id": "Lasso_ta_sentiment_high_vol_5d",
        "status": "CANDIDATE",
        "alpha": 2.0793,
        "p": 0.001784,
        "acc": 0.5461,
        "n_folds": 24
      },
      {
        "id": "Lasso_ta_sentiment_low_vol_5d",
        "status": "rejected",
        "alpha": 0.2106,
        "p": 0.454183,
        "acc": 0.5529,
        "n_folds": 24
      },
      {
        "id": "RandomForest_ta_sentiment_all_5d",
        "status": "CANDIDATE",
        "alpha": 1.6543,
        "p": 1e-06,
        "acc": 0.5816,
        "n_folds": 24
      },
      {
        "id": "RandomForest_ta_sentiment_high_vol_5d",
        "status": "CANDIDATE",
        "alpha": 2.8967,
        "p": 8.3e-05,
        "acc": 0.5757,
        "n_folds": 24
      },
      {
        "id": "RandomForest_ta_sentiment_low_vol_5d",
        "status": "CANDIDATE",
        "alpha": 0.7312,
        "p": 0.022896,
        "acc": 0.6114,
        "n_folds": 24
      },
      {
        "id": "GradientBoosting_ta_sentiment_all_5d",
        "status": "CANDIDATE",
        "alpha": 1.5886,
        "p": 0.0,
        "acc": 0.5618,
        "n_folds": 24
      },
      {
        "id": "GradientBoosting_ta_sentiment_high_vol_5d",
        "status": "CANDIDATE",
        "alpha": 2.8304,
        "p": 3.2e-05,
        "acc": 0.5847,
        "n_folds": 24
      },
      {
        "id": "GradientBoosting_ta_sentiment_low_vol_5d",
        "status": "raw_sig_fdr_fail",
        "alpha": 0.7133,
        "p": 0.042111,
        "acc": 0.6033,
        "n_folds": 24
      },
      {
        "id": "Ridge_all_features_all_5d",
        "status": "CANDIDATE",
        "alpha": 1.0362,
        "p": 0.002153,
        "acc": 0.5225,
        "n_folds": 24
      },
      {
        "id": "Ridge_all_features_high_vol_5d",
        "status": "CANDIDATE",
        "alpha": 1.554,
        "p": 0.020566,
        "acc": 0.5215,
        "n_folds": 24
      },
      {
        "id": "Ridge_all_features_low_vol_5d",
        "status": "CANDIDATE",
        "alpha": 0.7088,
        "p": 0.034821,
        "acc": 0.5874,
        "n_folds": 24
      },
      {
        "id": "Lasso_all_features_all_5d",
        "status": "CANDIDATE",
        "alpha": 1.2163,
        "p": 0.0001,
        "acc": 0.529,
        "n_folds": 24
      },
      {
        "id": "Lasso_all_features_high_vol_5d",
        "status": "CANDIDATE",
        "alpha": 1.7952,
        "p": 0.007724,
        "acc": 0.5274,
        "n_folds": 24
      },
      {
        "id": "Lasso_all_features_low_vol_5d",
        "status": "raw_sig_fdr_fail",
        "alpha": 0.6123,
        "p": 0.044033,
        "acc": 0.5701,
        "n_folds": 24
      },
      {
        "id": "RandomForest_all_features_all_5d",
        "status": "CANDIDATE",
        "alpha": 2.1053,
        "p": 0.0,
        "acc": 0.6057,
        "n_folds": 24
      },
      {
        "id": "RandomForest_all_features_high_vol_5d",
        "status": "CANDIDATE",
        "alpha": 3.3139,
        "p": 6e-06,
        "acc": 0.5975,
        "n_folds": 24
      },
      {
        "id": "RandomForest_all_features_low_vol_5d",
        "status": "CANDIDATE",
        "alpha": 1.2783,
        "p": 5.6e-05,
        "acc": 0.6611,
        "n_folds": 24
      },
      {
        "id": "GradientBoosting_all_features_all_5d",
        "status": "CANDIDATE",
        "alpha": 2.1701,
        "p": 0.0,
        "acc": 0.6061,
        "n_folds": 24
      },
      {
        "id": "GradientBoosting_all_features_high_vol_5d",
        "status": "CANDIDATE",
        "alpha": 3.7968,
        "p": 0.0,
        "acc": 0.6214,
        "n_folds": 24
      },
      {
        "id": "GradientBoosting_all_features_low_vol_5d",
        "status": "CANDIDATE",
        "alpha": 1.2394,
        "p": 0.001045,
        "acc": 0.6672,
        "n_folds": 24
      }
    ]
  },
  "updated": "2026-06-25T12:47:11Z"
}