{
  "updated": "2026-06-02T22:39:26Z",
  "mode": "active",
  "mode_detail": {
    "pillar_weights": true,
    "pillar_weights_regime": true,
    "confidence_threshold": true
  },
  "config": {
    "min_n_pillar": 30,
    "min_n_pillar_regime": 12,
    "min_n_threshold": 20,
    "alpha_scale": 5.0,
    "weight_clamp": [
      0.5,
      2.0
    ],
    "shrink_k": 20,
    "ema_alpha": 0.3,
    "candidates": [
      0.4,
      0.5,
      0.6,
      0.65,
      0.7,
      0.75,
      0.8,
      0.85
    ]
  },
  "market_drift": {
    "ema_offset_pct": -3.0485,
    "ema_alpha": 0.3
  },
  "input_summary": {
    "n_records": 2543,
    "n_actionable_5d": 477,
    "snapshot_count": 33,
    "gap_n_actionable": 1913,
    "gap_avg_abs_pct": 5.942,
    "gap_avg_signed_pct": -2.803,
    "gap_pillars_with_gradient": 6
  },
  "pillars": {
    "fundamental_score": {
      "n": 356,
      "alpha_pct": 1.497,
      "high_avg_pct": 2.68,
      "low_avg_pct": 1.183,
      "high_acc": 0.445,
      "low_acc": 0.448,
      "raw_weight_acc": 1.0749,
      "gap_delta": -0.0659,
      "raw_weight": 1.009,
      "shrunk_weight": 1.0085,
      "ema_weight": 1.0063,
      "applied": true,
      "reason": "n=356\u226530"
    },
    "quality_score": {
      "n": 356,
      "alpha_pct": -2.265,
      "high_avg_pct": 2.539,
      "low_avg_pct": 4.804,
      "high_acc": 0.402,
      "low_acc": 0.458,
      "raw_weight_acc": 0.8867,
      "gap_delta": -0.1,
      "raw_weight": 0.7867,
      "shrunk_weight": 0.7981,
      "ema_weight": 0.8031,
      "applied": true,
      "reason": "n=356\u226530"
    },
    "growth_score": {
      "n": 356,
      "alpha_pct": 0.13,
      "high_avg_pct": 2.545,
      "low_avg_pct": 2.415,
      "high_acc": 0.535,
      "low_acc": 0.402,
      "raw_weight_acc": 1.0065,
      "gap_delta": 0.0446,
      "raw_weight": 1.0511,
      "shrunk_weight": 1.0484,
      "ema_weight": 1.0795,
      "applied": true,
      "reason": "n=356\u226530"
    },
    "health_score": {
      "n": 356,
      "alpha_pct": 2.339,
      "high_avg_pct": 4.548,
      "low_avg_pct": 2.209,
      "high_acc": 0.373,
      "low_acc": 0.467,
      "raw_weight_acc": 1.117,
      "gap_delta": 0.047,
      "raw_weight": 1.164,
      "shrunk_weight": 1.1552,
      "ema_weight": 1.1462,
      "applied": true,
      "reason": "n=356\u226530"
    },
    "sentiment_score": {
      "n": 380,
      "alpha_pct": -1.342,
      "high_avg_pct": 1.496,
      "low_avg_pct": 2.838,
      "high_acc": 1.0,
      "low_acc": 0.417,
      "raw_weight_acc": 0.9329,
      "gap_delta": 0.1,
      "raw_weight": 1.0329,
      "shrunk_weight": 1.0313,
      "ema_weight": 1.031,
      "applied": true,
      "reason": "n=380\u226530"
    },
    "news_best_conf": {
      "n": 342,
      "alpha_pct": 3.193,
      "high_avg_pct": 5.151,
      "low_avg_pct": 1.958,
      "high_acc": 0.402,
      "low_acc": 0.493,
      "raw_weight_acc": 1.1597,
      "gap_delta": 0.1,
      "raw_weight": 1.2597,
      "shrunk_weight": 1.2453,
      "ema_weight": 1.2506,
      "applied": true,
      "reason": "n=342\u226530"
    },
    "insider_p_score": {
      "n": 0,
      "alpha_pct": null,
      "high_avg_pct": null,
      "low_avg_pct": null,
      "high_acc": null,
      "low_acc": null,
      "raw_weight_acc": 1.0,
      "gap_delta": 0.0,
      "raw_weight": 1.0,
      "shrunk_weight": 1.0,
      "ema_weight": 1.0,
      "applied": false,
      "reason": "no_signal"
    },
    "insider_score": {
      "n": 380,
      "alpha_pct": 4.737,
      "high_avg_pct": 7.014,
      "low_avg_pct": 2.277,
      "high_acc": 0.356,
      "low_acc": 0.457,
      "raw_weight_acc": 1.2369,
      "gap_delta": 0.0,
      "raw_weight": 1.2369,
      "shrunk_weight": 1.225,
      "ema_weight": 1.2078,
      "applied": true,
      "reason": "n=380\u226530"
    }
  },
  "pillars_by_regime": {
    "RISK-OFF": {
      "fundamental_score": {
        "n": 0,
        "alpha_pct": null,
        "high_avg_pct": null,
        "low_avg_pct": null,
        "high_acc": null,
        "low_acc": null,
        "raw_weight_acc": 1.0,
        "gap_delta": -0.0659,
        "raw_weight": 0.9341,
        "shrunk_weight": 1.0,
        "ema_weight": 1.0,
        "applied": false,
        "reason": "no_signal"
      },
      "quality_score": {
        "n": 0,
        "alpha_pct": null,
        "high_avg_pct": null,
        "low_avg_pct": null,
        "high_acc": null,
        "low_acc": null,
        "raw_weight_acc": 1.0,
        "gap_delta": -0.1,
        "raw_weight": 0.9,
        "shrunk_weight": 1.0,
        "ema_weight": 1.0,
        "applied": false,
        "reason": "no_signal"
      },
      "growth_score": {
        "n": 0,
        "alpha_pct": null,
        "high_avg_pct": null,
        "low_avg_pct": null,
        "high_acc": null,
        "low_acc": null,
        "raw_weight_acc": 1.0,
        "gap_delta": 0.0446,
        "raw_weight": 1.0446,
        "shrunk_weight": 1.0,
        "ema_weight": 1.0,
        "applied": false,
        "reason": "no_signal"
      },
      "health_score": {
        "n": 0,
        "alpha_pct": null,
        "high_avg_pct": null,
        "low_avg_pct": null,
        "high_acc": null,
        "low_acc": null,
        "raw_weight_acc": 1.0,
        "gap_delta": 0.047,
        "raw_weight": 1.047,
        "shrunk_weight": 1.0,
        "ema_weight": 1.0,
        "applied": false,
        "reason": "no_signal"
      },
      "sentiment_score": {
        "n": 0,
        "alpha_pct": null,
        "high_avg_pct": null,
        "low_avg_pct": null,
        "high_acc": null,
        "low_acc": null,
        "raw_weight_acc": 1.0,
        "gap_delta": 0.1,
        "raw_weight": 1.1,
        "shrunk_weight": 1.0,
        "ema_weight": 1.0,
        "applied": false,
        "reason": "no_signal"
      },
      "news_best_conf": {
        "n": 20,
        "alpha_pct": null,
        "high_avg_pct": 4.664,
        "low_avg_pct": null,
        "high_acc": 0.571,
        "low_acc": null,
        "raw_weight_acc": 1.0,
        "gap_delta": 0.1,
        "raw_weight": 1.1,
        "shrunk_weight": 1.0,
        "ema_weight": 1.0,
        "applied": false,
        "reason": "missing_tertile_pair"
      },
      "insider_p_score": {
        "n": 0,
        "alpha_pct": null,
        "high_avg_pct": null,
        "low_avg_pct": null,
        "high_acc": null,
        "low_acc": null,
        "raw_weight_acc": 1.0,
        "gap_delta": 0.0,
        "raw_weight": 1.0,
        "shrunk_weight": 1.0,
        "ema_weight": 1.0,
        "applied": false,
        "reason": "no_signal"
      },
      "insider_score": {
        "n": 0,
        "alpha_pct": null,
        "high_avg_pct": null,
        "low_avg_pct": null,
        "high_acc": null,
        "low_acc": null,
        "raw_weight_acc": 1.0,
        "gap_delta": 0.0,
        "raw_weight": 1.0,
        "shrunk_weight": 1.0,
        "ema_weight": 1.0,
        "applied": false,
        "reason": "no_signal"
      }
    },
    "RISK-ON": {
      "fundamental_score": {
        "n": 356,
        "alpha_pct": 1.497,
        "high_avg_pct": 2.68,
        "low_avg_pct": 1.183,
        "high_acc": 0.445,
        "low_acc": 0.448,
        "raw_weight_acc": 1.0749,
        "gap_delta": -0.0659,
        "raw_weight": 1.009,
        "shrunk_weight": 1.0085,
        "ema_weight": 1.0063,
        "applied": true,
        "reason": "n=356\u226512"
      },
      "quality_score": {
        "n": 356,
        "alpha_pct": -2.265,
        "high_avg_pct": 2.539,
        "low_avg_pct": 4.804,
        "high_acc": 0.402,
        "low_acc": 0.458,
        "raw_weight_acc": 0.8867,
        "gap_delta": -0.1,
        "raw_weight": 0.7867,
        "shrunk_weight": 0.7981,
        "ema_weight": 0.8031,
        "applied": true,
        "reason": "n=356\u226512"
      },
      "growth_score": {
        "n": 356,
        "alpha_pct": 0.13,
        "high_avg_pct": 2.545,
        "low_avg_pct": 2.415,
        "high_acc": 0.535,
        "low_acc": 0.402,
        "raw_weight_acc": 1.0065,
        "gap_delta": 0.0446,
        "raw_weight": 1.0511,
        "shrunk_weight": 1.0484,
        "ema_weight": 1.0795,
        "applied": true,
        "reason": "n=356\u226512"
      },
      "health_score": {
        "n": 356,
        "alpha_pct": 2.339,
        "high_avg_pct": 4.548,
        "low_avg_pct": 2.209,
        "high_acc": 0.373,
        "low_acc": 0.467,
        "raw_weight_acc": 1.117,
        "gap_delta": 0.047,
        "raw_weight": 1.164,
        "shrunk_weight": 1.1552,
        "ema_weight": 1.1462,
        "applied": true,
        "reason": "n=356\u226512"
      },
      "sentiment_score": {
        "n": 380,
        "alpha_pct": -1.342,
        "high_avg_pct": 1.496,
        "low_avg_pct": 2.838,
        "high_acc": 1.0,
        "low_acc": 0.417,
        "raw_weight_acc": 0.9329,
        "gap_delta": 0.1,
        "raw_weight": 1.0329,
        "shrunk_weight": 1.0313,
        "ema_weight": 1.031,
        "applied": true,
        "reason": "n=380\u226512"
      },
      "news_best_conf": {
        "n": 322,
        "alpha_pct": 2.851,
        "high_avg_pct": 5.126,
        "low_avg_pct": 2.275,
        "high_acc": 0.408,
        "low_acc": 0.464,
        "raw_weight_acc": 1.1425,
        "gap_delta": 0.1,
        "raw_weight": 1.2426,
        "shrunk_weight": 1.2284,
        "ema_weight": 1.2348,
        "applied": true,
        "reason": "n=322\u226512"
      },
      "insider_p_score": {
        "n": 0,
        "alpha_pct": null,
        "high_avg_pct": null,
        "low_avg_pct": null,
        "high_acc": null,
        "low_acc": null,
        "raw_weight_acc": 1.0,
        "gap_delta": 0.0,
        "raw_weight": 1.0,
        "shrunk_weight": 1.0,
        "ema_weight": 1.0,
        "applied": false,
        "reason": "no_signal"
      },
      "insider_score": {
        "n": 380,
        "alpha_pct": 4.737,
        "high_avg_pct": 7.014,
        "low_avg_pct": 2.277,
        "high_acc": 0.356,
        "low_acc": 0.457,
        "raw_weight_acc": 1.2369,
        "gap_delta": 0.0,
        "raw_weight": 1.2369,
        "shrunk_weight": 1.225,
        "ema_weight": 1.2078,
        "applied": true,
        "reason": "n=380\u226512"
      }
    }
  },
  "confidence_threshold": {
    "current_default": 0.7,
    "previous_ema": 0.8499,
    "sweep": [
      {
        "threshold": 0.4,
        "n": 375,
        "accuracy": 0.512,
        "avg_return_pct": 0.824,
        "score": 0.232
      },
      {
        "threshold": 0.5,
        "n": 366,
        "accuracy": 0.514,
        "avg_return_pct": 0.84,
        "score": 0.261
      },
      {
        "threshold": 0.6,
        "n": 356,
        "accuracy": 0.514,
        "avg_return_pct": 0.722,
        "score": 0.265
      },
      {
        "threshold": 0.65,
        "n": 349,
        "accuracy": 0.51,
        "avg_return_pct": 0.688,
        "score": 0.187
      },
      {
        "threshold": 0.7,
        "n": 289,
        "accuracy": 0.498,
        "avg_return_pct": 0.569,
        "score": -0.029
      },
      {
        "threshold": 0.75,
        "n": 165,
        "accuracy": 0.515,
        "avg_return_pct": 0.639,
        "score": 0.195
      },
      {
        "threshold": 0.8,
        "n": 73,
        "accuracy": 0.562,
        "avg_return_pct": 0.519,
        "score": 0.527
      },
      {
        "threshold": 0.85,
        "n": 26,
        "accuracy": 0.654,
        "avg_return_pct": 0.627,
        "score": 0.784
      }
    ],
    "recommended": 0.85,
    "best_score": 0.784,
    "best_n": 26,
    "best_accuracy": 0.654,
    "ema": 0.8499,
    "applied": true,
    "reason": "argmax_score n=26 acc=0.654"
  },
  "stop_loss": {
    "available": true,
    "n_completed": 35,
    "n_losses": 18,
    "n_stopped_out": 5,
    "n_take_profit": 0,
    "min_return_pct": -11.482,
    "max_return_pct": 9.419,
    "p10_return_pct": -10.481,
    "current_stop_loss_pct": -8.0,
    "recommendation": "hold_current",
    "reason": "insufficient_completed_trades_for_optimization"
  }
}