{"updated": "2026-05-01T22:11:11Z", "snapshot": [{"ticker": "QCOM", "date": "2026-05-01", "close": 177.01, "trend": "BEAR", "rsi14": 84.7629, "macd_hist": 4.9053, "bb_pct": 1.1037, "atr14": 7.0835, "hv20": 57.7735, "stoch_k": 85.28613333333334, "signals": ["rsi_overbought_84.8", "bb_upper_touch"], "recent_signals": 14}, {"ticker": "INTC", "date": "2026-05-01", "close": 99.62, "trend": "BULL", "rsi14": 88.2321, "macd_hist": 2.971, "bb_pct": 1.0228, "atr14": 4.7389, "hv20": 92.0749, "stoch_k": 97.90293333333334, "signals": ["rsi_overbought_88.2", "bb_upper_touch"], "recent_signals": 10}, {"ticker": "GOOGL", "date": "2026-05-01", "close": 385.69, "trend": "BULL", "rsi14": 86.8939, "macd_hist": 4.9409, "bb_pct": 1.0791, "atr14": 9.1503, "hv20": 35.8122, "stoch_k": 94.11373333333334, "signals": ["rsi_overbought_86.9", "bb_upper_touch"], "recent_signals": 9}, {"ticker": "NXPI", "date": "2026-05-01", "close": 295.24, "trend": "BEAR", "rsi14": 82.993, "macd_hist": 8.8464, "bb_pct": 1.0554, "atr14": 11.2729, "hv20": 83.6723, "stoch_k": 98.17399999999999, "signals": ["rsi_overbought_83.0", "bb_upper_touch"], "recent_signals": 9}, {"ticker": "AMZN", "date": "2026-05-01", "close": 268.26, "trend": "BEAR", "rsi14": 75.5479, "macd_hist": 1.2787, "bb_pct": 0.8361, "atr14": 7.3561, "hv20": 29.7559, "stoch_k": 83.35276666666667, "signals": ["rsi_overbought_75.5"], "recent_signals": 7}, {"ticker": "SPY", "date": "2026-05-01", "close": 720.65, "trend": "BULL", "rsi14": 76.5025, "macd_hist": 1.6422, "bb_pct": 0.806, "atr14": 6.5635, "hv20": 11.2816, "stoch_k": 92.87086666666666, "signals": ["rsi_overbought_76.5"], "recent_signals": 6}, {"ticker": "TLT", "date": "2026-05-01", "close": 85.61, "trend": "BEAR", "rsi14": 35.6102, "macd_hist": -0.0991, "bb_pct": -0.0541, "atr14": 0.5389, "hv20": 4.4168, "stoch_k": 12.622533333333335, "signals": ["bb_lower_touch"], "recent_signals": 6}, {"ticker": "AMD", "date": "2026-05-01", "close": 360.54, "trend": "BULL", "rsi14": 80.4436, "macd_hist": 7.4589, "bb_pct": 0.9311, "atr14": 15.2777, "hv20": 55.3264, "stoch_k": 95.59469999999999, "signals": ["rsi_overbought_80.4"], "recent_signals": 5}, {"ticker": "QQQ", "date": "2026-05-01", "close": 674.15, "trend": "BULL", "rsi14": 79.5549, "macd_hist": 2.9716, "bb_pct": 0.8623, "atr14": 8.1241, "hv20": 13.0301, "stoch_k": 96.93823333333334, "signals": ["rsi_overbought_79.6"], "recent_signals": 5}, {"ticker": "NVDA", "date": "2026-05-01", "close": 198.45, "trend": "BULL", "rsi14": 54.2685, "macd_hist": 0.0646, "bb_pct": 0.5581, "atr14": 5.5351, "hv20": 30.8649, "stoch_k": 53.8886, "signals": [], "recent_signals": 4}, {"ticker": "MU", "date": "2026-05-01", "close": 542.21, "trend": "BULL", "rsi14": 75.0073, "macd_hist": 8.5368, "bb_pct": 0.9575, "atr14": 25.5871, "hv20": 43.7856, "stoch_k": 90.75526666666667, "signals": ["rsi_overbought_75.0"], "recent_signals": 4}, {"ticker": "AAPL", "date": "2026-05-01", "close": 280.14, "trend": "BULL", "rsi14": 68.5369, "macd_hist": 0.9608, "bb_pct": 1.0081, "atr14": 6.1897, "hv20": 21.8668, "stoch_k": 74.2778, "signals": ["bb_upper_touch", "volume_spike_3.1x"], "recent_signals": 3}, {"ticker": "GLD", "date": "2026-05-01", "close": 423.18, "trend": "BULL", "rsi14": 41.9427, "macd_hist": -1.2915, "bb_pct": 0.1519, "atr14": 7.8961, "hv20": 15.9234, "stoch_k": 20.986533333333334, "signals": [], "recent_signals": 3}, {"ticker": "USO", "date": "2026-05-01", "close": 142.8, "trend": "BULL", "rsi14": 61.9376, "macd_hist": 1.2744, "bb_pct": 0.8194, "atr14": 6.769, "hv20": 74.0161, "stoch_k": 87.48063333333334, "signals": [], "recent_signals": 3}, {"ticker": "META", "date": "2026-05-01", "close": 608.745, "trend": "BEAR", "rsi14": 40.067, "macd_hist": -5.1975, "bb_pct": 0.2264, "atr14": 19.5305, "hv20": 46.0653, "stoch_k": 31.369199999999996, "signals": [], "recent_signals": 2}, {"ticker": "HYG", "date": "2026-05-01", "close": 80.06, "trend": "BEAR", "rsi14": 47.7025, "macd_hist": -0.0328, "bb_pct": 0.2815, "atr14": 0.2947, "hv20": 4.2094, "stoch_k": 33.98416666666667, "signals": [], "recent_signals": 2}, {"ticker": "MSFT", "date": "2026-05-01", "close": 414.44, "trend": "BEAR", "rsi14": 55.2919, "macd_hist": 0.7573, "bb_pct": 0.6171, "atr14": 10.4351, "hv20": 31.0258, "stoch_k": 71.63363333333332, "signals": [], "recent_signals": 1}, {"ticker": "AVGO", "date": "2026-05-01", "close": 421.28, "trend": "BULL", "rsi14": 68.9385, "macd_hist": 0.8738, "bb_pct": 0.7717, "atr14": 12.4576, "hv20": 40.7028, "stoch_k": 78.23946666666666, "signals": [], "recent_signals": 1}, {"ticker": "ASML", "date": "2026-05-01", "close": 1427.02, "trend": "BULL", "rsi14": 51.4642, "macd_hist": -5.1185, "bb_pct": 0.4779, "atr14": 44.1884, "hv20": 44.6634, "stoch_k": 33.0342, "signals": [], "recent_signals": 1}, {"ticker": "JPM", "date": "2026-05-01", "close": 312.47, "trend": "BEAR", "rsi14": 58.1069, "macd_hist": -0.3376, "bb_pct": 0.6253, "atr14": 5.739, "hv20": 18.0966, "stoch_k": 42.89993333333334, "signals": [], "recent_signals": 1}, {"ticker": "BAC", "date": "2026-05-01", "close": 53.24, "trend": "BEAR", "rsi14": 58.1717, "macd_hist": -0.1103, "bb_pct": 0.5783, "atr14": 1.1233, "hv20": 20.4936, "stoch_k": 38.18856666666667, "signals": [], "recent_signals": 1}, {"ticker": "GS", "date": "2026-05-01", "close": 923.71, "trend": "BULL", "rsi14": 57.0981, "macd_hist": -1.3219, "bb_pct": 0.6283, "atr14": 23.3887, "hv20": 31.0326, "stoch_k": 56.05236666666667, "signals": [], "recent_signals": 1}, {"ticker": "MS", "date": "2026-05-01", "close": 190.17, "trend": "BULL", "rsi14": 64.2583, "macd_hist": -0.2417, "bb_pct": 0.6726, "atr14": 4.6084, "hv20": 27.5872, "stoch_k": 69.12976666666667, "signals": [], "recent_signals": 1}, {"ticker": "XOM", "date": "2026-05-01", "close": 152.75, "trend": "BULL", "rsi14": 49.6586, "macd_hist": 0.429, "bb_pct": 0.5378, "atr14": 4.2132, "hv20": 34.9423, "stoch_k": 87.6435, "signals": [], "recent_signals": 1}, {"ticker": "CVX", "date": "2026-05-01", "close": 190.63, "trend": "BULL", "rsi14": 50.0821, "macd_hist": 0.6148, "bb_pct": 0.5799, "atr14": 4.8316, "hv20": 32.2046, "stoch_k": 89.39016666666667, "signals": [], "recent_signals": 1}, {"ticker": "DIA", "date": "2026-05-01", "close": 495.02, "trend": "BULL", "rsi14": 61.7562, "macd_hist": 0.5362, "bb_pct": 0.7282, "atr14": 5.4204, "hv20": 15.3144, "stoch_k": 74.57186666666666, "signals": [], "recent_signals": 1}, {"ticker": "TSLA", "date": "2026-05-01", "close": 390.82, "trend": "BEAR", "rsi14": 55.9317, "macd_hist": 1.9817, "bb_pct": 0.7651, "atr14": 14.0686, "hv20": 46.2924, "stoch_k": 57.66223333333334, "signals": [], "recent_signals": 0}, {"ticker": "BLK", "date": "2026-05-01", "close": 1061.6801, "trend": "BEAR", "rsi14": 61.1203, "macd_hist": 1.8289, "bb_pct": 0.7128, "atr14": 23.8389, "hv20": 28.5797, "stoch_k": 71.84113333333333, "signals": [], "recent_signals": 0}, {"ticker": "IWM", "date": "2026-05-01", "close": 279.28, "trend": "BULL", "rsi14": 67.1104, "macd_hist": 0.2994, "bb_pct": 0.7833, "atr14": 4.2119, "hv20": 17.8315, "stoch_k": 82.84943333333334, "signals": [], "recent_signals": 0}]}